Workbook

Sheet Master data
D1: Support coverage | F1: ROI
B2: High | C2: 3 | D2: 3 | F2: >24 | G2: 1
B3: Medium | C3: 2 | D3: 2 | F3: >12 <=24 | G3: 2
B4: Low | C4: 1 | D4: 1 | F4: <=12 | G4: 3

Sheet Agents ACN prio
C1: Current State (Readiness) | K1: Expected RoI (Value) | Q1: Go To Market Priority | S1: Score
B2: Digital Agent | C2: Standardization | D2: Standardization Score | E2: Adoption | F2: Adoption Score | G2: Data availability & Quality | H2: Data score | I2: Support Coverage | J2: Support Score | K2: Cost Avoidance | L2: Cost Score | M2: Sales & Profitability | N2: Revenue Score | O2: Time to value (Months) | P2: TtV Score
A3: Lead-to-Order | B3: Master Data Quality Agent | C3: High | D3: =IFERROR(VLOOKUP(C3,'Master data'!$B$2:$C$4,2,FALSE),0) | E3: Medium | F3: =IFERROR(VLOOKUP(E3,'Master data'!$B$2:$C$4,2,FALSE),0) | G3: High | H3: =IFERROR(VLOOKUP(G3,'Master data'!$B$2:$C$4,2,FALSE),0) | I3: Medium | J3: =IFERROR(VLOOKUP(I3,'Master data'!$B$2:$D$4,3,FALSE),0) | K3: High | L3: =IFERROR(VLOOKUP(K3,'Master data'!$B$2:$C$4,2,FALSE),0) | M3: Medium | N3: =IFERROR(VLOOKUP(M3,'Master data'!$B$2:$C$4,2,FALSE),0) | O3: <=12 | P3: =IFERROR(VLOOKUP(O3,'Master data'!$F$2:$G$4,2,FALSE),0) | R3: =IF(Q3="X",1,0) | S3: =SUM(D3,F3,H3,J3,L3,N3,P3,R3)
B4: Quote Configuration Agent | C4: Low | D4: =IFERROR(VLOOKUP(C4,'Master data'!$B$2:$C$4,2,FALSE),0) | E4: Low | F4: =IFERROR(VLOOKUP(E4,'Master data'!$B$2:$C$4,2,FALSE),0) | G4: Medium | H4: =IFERROR(VLOOKUP(G4,'Master data'!$B$2:$C$4,2,FALSE),0) | I4: Low | J4: =IFERROR(VLOOKUP(I4,'Master data'!$B$2:$D$4,3,FALSE),0) | K4: High | L4: =IFERROR(VLOOKUP(K4,'Master data'!$B$2:$C$4,2,FALSE),0) | M4: High | N4: =IFERROR(VLOOKUP(M4,'Master data'!$B$2:$C$4,2,FALSE),0) | O4: >12 <=24 | P4: =IFERROR(VLOOKUP(O4,'Master data'!$F$2:$G$4,2,FALSE),0) | R4: =IF(Q4="X",1,0) | S4: =SUM(D4,F4,H4,J4,L4,N4,P4,R4)
B5: Credit Decision Agent | C5: High | D5: =IFERROR(VLOOKUP(C5,'Master data'!$B$2:$C$4,2,FALSE),0) | E5: Medium | F5: =IFERROR(VLOOKUP(E5,'Master data'!$B$2:$C$4,2,FALSE),0) | G5: High | H5: =IFERROR(VLOOKUP(G5,'Master data'!$B$2:$C$4,2,FALSE),0) | I5: Medium | J5: =IFERROR(VLOOKUP(I5,'Master data'!$B$2:$D$4,3,FALSE),0) | K5: High | L5: =IFERROR(VLOOKUP(K5,'Master data'!$B$2:$C$4,2,FALSE),0) | M5: High | N5: =IFERROR(VLOOKUP(M5,'Master data'!$B$2:$C$4,2,FALSE),0) | O5: <=12 | P5: =IFERROR(VLOOKUP(O5,'Master data'!$F$2:$G$4,2,FALSE),0) | R5: =IF(Q5="X",1,0) | S5: =SUM(D5,F5,H5,J5,L5,N5,P5,R5)
B6: Compliance Orchestration Agent | C6: Medium | D6: =IFERROR(VLOOKUP(C6,'Master data'!$B$2:$C$4,2,FALSE),0) | E6: Medium | F6: =IFERROR(VLOOKUP(E6,'Master data'!$B$2:$C$4,2,FALSE),0) | G6: High | H6: =IFERROR(VLOOKUP(G6,'Master data'!$B$2:$C$4,2,FALSE),0) | I6: Medium | J6: =IFERROR(VLOOKUP(I6,'Master data'!$B$2:$D$4,3,FALSE),0) | K6: High | L6: =IFERROR(VLOOKUP(K6,'Master data'!$B$2:$C$4,2,FALSE),0) | M6: High | N6: =IFERROR(VLOOKUP(M6,'Master data'!$B$2:$C$4,2,FALSE),0) | O6: >12 <=24 | P6: =IFERROR(VLOOKUP(O6,'Master data'!$F$2:$G$4,2,FALSE),0) | R6: =IF(Q6="X",1,0) | S6: =SUM(D6,F6,H6,J6,L6,N6,P6,R6)
B7: Quote Routing & Approval Agent | C7: High | D7: =IFERROR(VLOOKUP(C7,'Master data'!$B$2:$C$4,2,FALSE),0) | E7: Medium | F7: =IFERROR(VLOOKUP(E7,'Master data'!$B$2:$C$4,2,FALSE),0) | G7: High | H7: =IFERROR(VLOOKUP(G7,'Master data'!$B$2:$C$4,2,FALSE),0) | I7: High | J7: =IFERROR(VLOOKUP(I7,'Master data'!$B$2:$D$4,3,FALSE),0) | K7: Medium | L7: =IFERROR(VLOOKUP(K7,'Master data'!$B$2:$C$4,2,FALSE),0) | M7: High | N7: =IFERROR(VLOOKUP(M7,'Master data'!$B$2:$C$4,2,FALSE),0) | O7: <=12 | P7: =IFERROR(VLOOKUP(O7,'Master data'!$F$2:$G$4,2,FALSE),0) | R7: =IF(Q7="X",1,0) | S7: =SUM(D7,F7,H7,J7,L7,N7,P7,R7)
B8: Quote Conversion Agent | C8: Medium | D8: =IFERROR(VLOOKUP(C8,'Master data'!$B$2:$C$4,2,FALSE),0) | E8: Medium | F8: =IFERROR(VLOOKUP(E8,'Master data'!$B$2:$C$4,2,FALSE),0) | G8: High | H8: =IFERROR(VLOOKUP(G8,'Master data'!$B$2:$C$4,2,FALSE),0) | I8: Medium | J8: =IFERROR(VLOOKUP(I8,'Master data'!$B$2:$D$4,3,FALSE),0) | K8: Medium | L8: =IFERROR(VLOOKUP(K8,'Master data'!$B$2:$C$4,2,FALSE),0) | M8: High | N8: =IFERROR(VLOOKUP(M8,'Master data'!$B$2:$C$4,2,FALSE),0) | O8: <=12 | P8: =IFERROR(VLOOKUP(O8,'Master data'!$F$2:$G$4,2,FALSE),0) | R8: =IF(Q8="X",1,0) | S8: =SUM(D8,F8,H8,J8,L8,N8,P8,R8)
A9: Order-to-Cash | N9: =IFERROR(VLOOKUP(M9,'Master data'!$B$2:$C$4,2,FALSE),0) | P9: =IFERROR(VLOOKUP(O9,'Master data'!$F$2:$G$4,2,FALSE),0) | Q9: X | R9: =IF(Q9="X",1,0) | S9: =SUM(D9,F9,H9,J9,L9,N9,P9,R9)
N10: =IFERROR(VLOOKUP(M10,'Master data'!$B$2:$C$4,2,FALSE),0) | P10: =IFERROR(VLOOKUP(O10,'Master data'!$F$2:$G$4,2,FALSE),0) | R10: =IF(Q10="X",1,0) | S10: =SUM(D10,F10,H10,J10,L10,N10,P10,R10)
N11: =IFERROR(VLOOKUP(M11,'Master data'!$B$2:$C$4,2,FALSE),0) | P11: =IFERROR(VLOOKUP(O11,'Master data'!$F$2:$G$4,2,FALSE),0) | R11: =IF(Q11="X",1,0) | S11: =SUM(D11,F11,H11,J11,L11,N11,P11,R11)
N12: =IFERROR(VLOOKUP(M12,'Master data'!$B$2:$C$4,2,FALSE),0) | P12: =IFERROR(VLOOKUP(O12,'Master data'!$F$2:$G$4,2,FALSE),0) | R12: =IF(Q12="X",1,0) | S12: =SUM(D12,F12,H12,J12,L12,N12,P12,R12)
D13: =IFERROR(VLOOKUP(C13,'Master data'!$B$2:$C$4,2,FALSE),0) | R13: =IF(Q13="X",1,0)
D14: =IFERROR(VLOOKUP(C14,'Master data'!$B$2:$C$4,2,FALSE),0) | R14: =IF(Q14="X",1,0)
D15: =IFERROR(VLOOKUP(C15,'Master data'!$B$2:$C$4,2,FALSE),0) | R15: =IF(Q15="X",1,0)
D16: =IFERROR(VLOOKUP(C16,'Master data'!$B$2:$C$4,2,FALSE),0) | R16: =IF(Q16="X",1,0)
D17: =IFERROR(VLOOKUP(C17,'Master data'!$B$2:$C$4,2,FALSE),0) | R17: =IF(Q17="X",1,0)
D18: =IFERROR(VLOOKUP(C18,'Master data'!$B$2:$C$4,2,FALSE),0) | R18: =IF(Q18="X",1,0)
D19: =IFERROR(VLOOKUP(C19,'Master data'!$B$2:$C$4,2,FALSE),0) | R19: =IF(Q19="X",1,0)
D20: =IFERROR(VLOOKUP(C20,'Master data'!$B$2:$C$4,2,FALSE),0) | R20: =IF(Q20="X",1,0)
D21: =IFERROR(VLOOKUP(C21,'Master data'!$B$2:$C$4,2,FALSE),0) | R21: =IF(Q21="X",1,0)
D22: =IFERROR(VLOOKUP(C22,'Master data'!$B$2:$C$4,2,FALSE),0) | R22: =IF(Q22="X",1,0)
D23: =IFERROR(VLOOKUP(C23,'Master data'!$B$2:$C$4,2,FALSE),0) | R23: =IF(Q23="X",1,0)
D24: =IFERROR(VLOOKUP(C24,'Master data'!$B$2:$C$4,2,FALSE),0) | R24: =IF(Q24="X",1,0)
... D51: =IFERROR(VLOOKUP(C51,'Master data'!$B$2:$C$4,2,FALSE),0) | R51: =IF(Q51="X",1,0)

Sheet ACN Agentfactory
A2: # | B2: ACCOUNT | C2: Flag (ignore) | D2: REGION | E2: INDUSTRY | F2: USE CASES (including Agent Name) | G2: Project POC (Ent ID) | H2: Project Status (Pipeline, In Progress, Completed) | I2: Production Status (In Production, In development, On Hold) | J2: Reasoning for Production / No Production | K2: Roadmap Created? (Yes/No) | L2: Funding Type (Salesforce Funded, Accenture Funded, Client Funded) | M2: Owner
D3: (AMERICA/EMEA/APAC/Innovation/Others)
A4: 1 | B4: Illumina | D4: AMERICA | E4: Life Science | F4: Knowledge Grounded Emails, | H4: Completed | I4: In Production | J4: Market Demand | K4: No | L4: Client funded | M4: Sitansu
F5: Case Summaries, and generate email with integrated order data from salesforce
A6: 2 | B6: Boston Scientific | D6: AMERICA | E6: Life Science | F6: Knowledge Grounded Emails, Account Summaries, and voice to action while logging a call in salesforce | H6: Completed | I6: In Production | J6: Market Demand | K6: No | L6: Client funded | M6: Sitansu
A7: 3 | B7: Stryker 1.0 | D7: AMERICA | E7: Life Science | F7: Duplicate case retrieval and case update.Identfying missing information in a case and showing it in the agent conversation.Data cloud reports/Dashboard for monitoring credits getting consumed in each session , as well as user based consumtion.Updatring the agentic conversation in the custom rich text field in Salesforce.Drafting an email with the summary so that it can be sent to the user. | H7: Completed | I7: In Production
A8: 4 | B8: Stryker 2.0 | D8: AMERICA | E8: Life Science | F8: Implemented the requirement of Stryker 1.0 with Employee Agent.Also Created few more reports Data cloud reports for the Agent Credits consumption with respect to specific employee agent. | H8: Completed | I8: In Production
A9: 5 | B9: CES SF POC | D9: AMERICA | E9: Telecom | F9: Enhanced Agentforce capabilities by integrating it with the Google CES agent using the Agent API.Leveraged Data cloud Data library to store the knowledge articles which can be used by the agent to suggest trouble shooting steps before actually suggesting an upgraded Internet plan. | H9: Completed | I9: In Production
A10: 6 | B10: Marriott | D10: AMERICA | E10: PRD | F10: Created a Employee Agent default for Marriott internal service rep. This use case was built to reduce the manual efforts of service representatives to search the latest facts of Marriott Properties hosted on 3rd party app. Agent will search the exact answer to the query and summarize it rather than searching up the whole hotel fact sheet. Agent will also be able to handle queries from knowledge it will summarize the related articles using RAG search. | H10: Completed | I10: In Production | K10: No | L10: Client funded | M10: Neetu
A11: 7 | B11: Salesforce | D11: AMERICA | E11: CMT | F11: Created a custom employee agent for Account Success team.This Employee Agent will assist for more than 2,600 CSM users/managers to assist with creating, updating, and closing Engagements. This CSM agent also offers extra capabilities like summarizing the Success Path, calculating sentiment scores, Search web & Slack and handling team assignments. Furthermore, Accenture created a Sales Coach for the Success Overview custom object.​ | H11: In Progress | I11: In Production | K11: No | L11: Client funded | M11: Neetu
A12: 8 | B12: Proactive Adoption Agent​ ​ | D12: AMERICA | E12: Technology | F12: An AI-powered agent assesses customer adoption of specific features and provides personalized guidance to enhance usage. If adoption is low, it educates users on feature value, onboarding, and best practices while checking understanding and sharing relevant resources. For premier and signature customers, the agent facilitates Guide Engagements or expert-led coaching sessions to drive deeper adoption.​ | H12: In Progress | I12: In Development
A13: 9 | B13: McKesson | D13: AMERICA | E13: Healthcare | F13: An AI-powered agent autonomously identify missing information from a customer email and auto-generate a targeted and concise response to collect missing information, | H13: Completed | I13: In Production | J13: Market Demand | K13: No | L13: Clinet Funded | M13: Sitansu
F14: Recommend knowledge articles to support the customer request and use selected article in response generation,
F15: Generate a case summary with customer sentiment
F16: Take in additional thread context from the case beyond incoming email (started)
A17: 10 | B17: Net Zero Cloud | D17: AMERICA | E17: Sustainibility | F17: The FY25 Supplier Portal roadmap uses Generative AI and deep data integration to modernize procurement—shifting from manual reviews to automated, insight-driven decision-making. | H17: Completed | I17: In Production
F18: Core capabilities and value:
F19: GenAI Supplier Assessment: Automatically analyzes supplier surveys to assess decarbonization readiness, delivering faster, actionable insights.
F20: AI ESG Scoring: Applies a consistent, configurable AI framework to score and benchmark supplier sustainability performance.
F21: Supplier Profile Dashboard: Provides a centralized, visual view of ESG ratings, risks, trends, and action items for greater transparency.
F22: ESG Compass (for Suppliers): Enables peer benchmarking and guidance to help suppliers identify gaps and improve ESG performance.
F23: Supplier Improvement Plans: Auto-generates tailored improvement actions to drive accountability, risk mitigation, and progress.
F24: Overall impact:
F25: Faster insights, data-driven ESG decisions, improved transparency, proactive risk management, and stronger supplier engagement on sustainability and decarbonization.
A26: 11 | B26: ACIS | D26: AMERICA | E26: Public Sector | F26: 1. Agent should automate the intake process by listening to callers and populating fields in any order. Data should be captured in a structured format. Call should be automatically transcribed as the call is going. | H26: In Progress | I26: In Development | K26: Yes | L26: Accenture Funded | M26: Ankur Omar
F27: 2. Agent should generate appropriate forms based on data received from the call.
F28: 3. Agent should coach the caseworker to ensure all required information is captured (even if out of order or incorrect). For example, if the address is not correct, the agent should prompt user to fix it (in real-time). Or prompt back if data is missing.
F29: Summarize of case
F30: 4. Agent should recommends services/programs proven effective for similar demographic profiles
A31: 12 | B31: Virtual Sales Agent | E31: Auto Cloud
A32: 13 | B32: Proactive Service Agent | E32: Auto Cloud
A33: 14 | B33: B2B Sales | D33: AMERICA | E33: Sales Cloud | F33: Key Themes & Use Cases for B2B Sales: | G33: manoj.b.kumar.mishra | H33: In Progress | I33: In Production | J33: Market Demand | K33: Yes | L33: Accenture Funded | M33: Manoj
F34: AI-Driven Sales Productivity (Employee Agent):
F36: 1. Daily task prioritization and prospecting
F37: 2. Automated opportunity and quote creation
F38: 3. Intelligent product and discount recommendations
F39: 4. End-to-end quote lifecycle management
F40: 5. Transcript summarization and follow-up scheduling
F41: Customer Retention & Insights (Employee Agent):
F42: 1. Proactive churn detection using usage and sentiment data
F43: 2. Suggested retention actions (emails, follow-up tasks)
F44: 3. Integrated real-time knowledge and insights for sales reps (Employee Agent & ADL)
F45: Sales Enablement & Coaching:
F46: 1. Sales Coach Agent provides real-time coaching and personalized feedback based on performance and call data
... F48: 1. Slack Agent routes notifications and approval requests directly to Slack for faster action

Sheet Agents Siemens criteria
A1: Super Agent Use Case | B1: Sub-Agent Use Cases | C1: Agent Description (short) | D1: Pain Point Addressed | E1: Agent Technology | F1: Agent Specification | K1: Existing ACN Assets | L1: Siemens Criteria | X1: Value x Effort
F2: Host System | G2: Input (Sources/Supplier) | H2: How does this agent technically work? | I2: Agent Output | J2: KPIs to measure business impact | L2: Business Value Potential | N2: Cross-business Applicability | P2: Technical Complexity & Feasibility | R2: Data readiness and ACP compliance | T2: Alignment with existing initiatives | V2: User Impact & Adoption Potential | X2: Business Value | Z2: Implementation Effort
K3: High | L3: Major penalty/loss prevention and/or direct revenue/profit driver + time to value < 3 months | N3: Applicable across all business divisions with minimal customization | P3: Requires integration across multiple systems with different technologies (e.g., Salesforce + SAP + others), complex data orchestration needs | R3: Meets requirements: Use case can be implemented with ACP Level 2 or lower | T3: Complements existing initiatives, creates synergies | V3: Addresses Siemens pain point and a large user base that is employee-facing (e.g. Sales Reps) | X3: =L3 | Z3: Requires >6 months
K4: Medium | L4: Moderate efficiency gains and/or indirect contribution + time to value 3-6 months | N4: Widely applicable but requires some customization per business division | P4: Requires integration between 1-2 systems on similar technology (e.g., multiple Salesforce orgs), standard data requirements | R4: - | T4: No overlap, independent initiative | V4: Addresses Siemens pain point and a affects a smaller number of user or user base is customer-facing | X4: =L4 | Z4: Requires 3-6 months
K5: Low | L5: Minor savings and/or cost savings only + time to value > 6 months | N5: Limited to single business division or single use case | P5: Self-contained within one system (e.g., Salesforce), no external integrations required, aligns with existing AI standards | R5: Does not meet requirements: Requires ACP Level 3 or higher (potential blocker) | T5: Duplicates existing efforts or conflicts with current business roadmap(s) | V5: Does not address a Siemens pain point | X5: =L5 | Z5: Can be implemented in ≤3 months
F6: What system does the agent mostly operate in | G6: What are the input sources | H6: What does the agent do, from trigger to operating mode | I6: What is the agents output | J6: How can we determine the value of each agent | K6: ACN Agentfactory | L6: The agents should be able to provide quick wins and demonstrate measurable business impact, such as improved productivity, cost savings, or revenue generation. | N6: The agents should not be limited to a specific business division (e.g., DI or SI) but should be applicable across the organization. | P6: The agents should be feasible to implement within the existing technical constraints and align with Siemens' AI standards and orchestration capabilities (e.g. data cloud capabilities). | R6: The agents should not require level 3 as this would be an additional challenge (e.g. SieSales currently has ACP level 2 data). | T6: The agents should not duplicate efforts or overlap with the agent use cases already being worked on by the team. -> No overlap (no), yes there are similar use cases already worked on based on SI/DI/Agentforce use cases (yes) | V6: The agents should address the needs of a significant user base and target specific pain points or gaps in the current CRM usage. | X6: As before based on "cost avoidance", "sales & profitability" and "time to value (months)". -> see "Business Value Potential" | Z6: Based on implementation time.
A7: Master Data Quality Agent | B7: Duplicate Detection Sub-Agent | C7: Identifies and flags duplicate customer records across systems using fuzzy matching algorithms | D7: Data fragmentation across multiple CRM/ERP systems leading to duplicate customer records, inconsistent account hierarchies, and wasted sales effort on same prospects | E7: Salesforce Einstein, ML-based fuzzy matching, Probabilistic record linkage algorithms | F7: SAP MDG | G7: Customer records (SF CRM, MDG); Fuzzy matching rules; Historical duplicate patterns | H7: Triggered on new/changed customer records. Runs ML-based similarity algorithms to identify potential duplicates across name, address, tax ID. Scores matches and flags high-confidence duplicates for auto-merge or review. | I7: Duplicate alerts with confidence score; Merge recommendations; Auto-merge execution (>95% confidence) | J7: Duplicate detection rate; False positive rate; Auto-merge accuracy | L7: High, Medium or Low | M7: [Reasoning] | N7: High, Medium or Low | O7: [Reasoning] | P7: High, Medium or Low | Q7: [Reasoning] | R7: High or Low | S7: [Reasoning] | T7: High, Medium or Low | U7: [Reasoning] | V7: High, Medium or Low | W7: [Reasoning] | X7: =L7 | Y7: [Reasoning] | Z7: High, Medium or Low | AA7: [Reasoning]
A8: Master Data Quality Agent | B8: Address Validation Sub-Agent | F8: SAP MDG | G8: Address data from all sources; Postal database feeds; Geolocation services | H8: Triggered on address creation/update. Calls external address validation APIs, standardizes formats, verifies deliverability, enriches with geolocation data. Auto-corrects minor errors and flags major issues. | I8: Validated addresses; Correction suggestions; Validation status flags; Geocoordinates | J8: Validation success rate; Auto-correction rate; Delivery failure reduction | X8: =L8
A9: Master Data Quality Agent | B9: Data Completeness Sub-Agent | F9: SAP MDG | G9: Customer master records; Required field definitions by segment; Business rules repository | H9: Triggered on record save. Evaluates completeness based on customer segment, transaction type, and regulatory requirements. Calculates completeness scores and identifies missing critical data. | I9: Completeness score (0-100); Missing field alerts; Priority ranking; Enrichment recommendations | J9: Overall completeness score; Critical field completion rate; Time to complete records | X9: =L9
A10: Master Data Quality Agent | B10: Data Consistency Sub-Agent | F10: SAP MDG | G10: Multi-system customer data; Cross-reference rules; Hierarchy validations | H10: Triggered on sync events. Compares customer data across CRM, ERP, billing systems. Detects inconsistencies in account hierarchies, payment terms, credit limits. Applies resolution rules or escalates conflicts. | I10: Consistency violation reports; Auto-reconciliation actions; Conflict resolution recommendations | J10: Data consistency score; Cross-system sync errors; Reconciliation time | X10: =L10
A11: Master Data Quality Agent | B11: Data Change Monitoring Sub-Agent | F11: SAP MDG | G11: Change logs from all systems; Audit rules; Suspicious pattern definitions | H11: Continuously monitors data changes. Detects anomalous patterns (bulk changes, unauthorized modifications, rapid updates). Triggers alerts for suspicious activities and maintains audit trail. | I11: Change history reports; Anomaly alerts; Audit documentation; Rollback triggers | J11: Anomaly detection rate; Audit compliance score; Mean time to detect issues | X11: =L11
A12: Quote Configuration Agent | B12: Product Recommendation Sub-Agent | F12: SF RCA | G12: Customer requirements; Customer profile & history; Product catalog; Pricing rules | H12: Triggered when quote initiated. Analyzes customer needs, industry, size, purchase history. Runs recommendation engine to suggest products, bundles, and configurations. Considers margin optimization and inventory availability. | I12: Recommended products ranked by fit; Bundle suggestions; Alternative options; Justification rationale | J12: Recommendation acceptance rate; Upsell success rate; Quote value increase | K12: Automated opportunity and quote creation | X12: =L12
A13: Quote Configuration Agent | B13: Pricing Optimization Sub-Agent | F13: SF RCA | G13: Product selections; Pricing rules & matrices; Competitive intelligence; Customer agreements | H13: Triggered after product selection. Calculates optimal pricing considering volume discounts, contract terms, competitive positioning, margin targets. Suggests discount levels and validates against approval thresholds. | I13: Optimized pricing; Discount recommendations; Pricing rationale; Margin analysis; Approval requirements | J13: Win rate by pricing tier; Margin realization; Discount variance | K13: Intelligent product and discount recommendations | X13: =L13
A14: Quote Configuration Agent | B14: Technical Feasibility Sub-Agent | F14: SF RCA | G14: Product configurations; Technical compatibility rules; Engineering constraints; Customer environment data | H14: Triggered during configuration. Validates technical compatibility of selected products, checks for conflicts, verifies installation requirements. Flags engineering review needs for custom configurations. | I14: Feasibility assessment; Configuration warnings; Engineering escalation flags; Alternative configurations | J14: Configuration error rate; Engineering escalation rate; First-time-right quotes | X14: =L14
A15: Quote Configuration Agent | B15: Upsell/Cross-sell Opportunity Sub-Agent | F15: SF RCA | G15: Current quote items; Customer installed base; Product affinity rules; Campaign data | H15: Triggered during quote building. Identifies relevant add-ons, upgrades, complementary products based on what's in cart and customer history. Scores opportunities by likelihood and value. | I15: Ranked upsell opportunities; Cross-sell suggestions; Value messaging; Success probability scores | J15: Attach rate; Average deal size increase; Opportunity conversion rate | X15: =L15
A16: Quote Configuration Agent | B16: Quote Validation Sub-Agent | F16: SF RCA | G16: Complete quote data; Business rules; Approval policies; Historical won/lost data | H16: Triggered before quote submission. Performs comprehensive validation of pricing, discounts, configurations, terms. Checks completeness, compliance with policies. Determines required approval routing. | I16: Validation results; Error/warning list; Approval routing decision; Risk assessment | J16: Quote error rate; Rework percentage; Time to validate | X16: =L16
A17: Credit Decision Agent | B17: Credit Data Aggregation Sub-Agent | F17: SAP S/4HANA | G17: Credit bureau APIs (cFIN); Domain screening (EDS); Contact data (Contarget); Internal AR history | H17: Triggered on credit check request. Orchestrates parallel API calls to multiple credit bureaus and screening services. Consolidates responses, handles timeouts/errors, enriches with internal payment history data. | I17: Consolidated credit report; Bureau scores; Screening results; Payment history summary | J17: Data retrieval time; API success rate; Data completeness | X17: =L17
A18: Credit Decision Agent | B18: Risk Scoring Sub-Agent | F18: SAP S/4HANA | G18: Aggregated credit data; Corporate hierarchy; Industry benchmarks; Current exposure | H18: Triggered after data aggregation. Applies ML-based risk model incorporating bureau scores, payment patterns, industry risk, corporate structure. Calculates probability of default and expected loss. | I18: Risk score (0-1000); Risk category (A-E); Default probability; Contributing risk factors | J18: Model accuracy (vs. actual defaults); Score stability; Prediction power | X18: =L18
A19: Credit Decision Agent | B19: Credit Limit Calculation Sub-Agent | F19: SAP S/4HANA | G19: Risk score; Financial statements; Order value; Payment terms; Existing exposure | H19: Triggered after risk scoring. Calculates recommended credit limit using risk-based pricing models, considers requested amount, existing exposure, collateral. Optimizes for risk-adjusted return. | I19: Recommended credit limit; Limit justification; Required collateral/guarantees; Monitoring thresholds | J19: Limit utilization rate; Credit losses; Revenue at risk | X19: =L19
A20: Credit Decision Agent | B20: Approval Routing Sub-Agent | F20: SAP S/4HANA | G20: Risk assessment results; Credit limit recommendation; Approval policies; Organizational hierarchy | H20: Triggered after limit calculation. Determines approval requirements based on risk level, amount, policy exceptions. Routes to appropriate approvers, sets SLAs, manages escalations for overdue approvals. | I20: Approval workflow route; Required approver list; Justification package; SLA timers | J20: Auto-approval rate; Approval cycle time; Escalation rate | K20: Slack Agent routes notifications and approval requests directly to Slack for faster action | X20: =L20
A21: Credit Decision Agent | B21: Credit Monitoring Sub-Agent | F21: SAP S/4HANA | G21: Approved credit limits; Transaction activity; Credit bureau alerts; Payment performance | H21: Continuously monitors approved customers. Tracks credit utilization, payment timeliness, bureau score changes. Triggers alerts for deteriorating conditions, recommends limit adjustments or holds. | I21: Monitoring alerts; Limit adjustment recommendations; Payment hold triggers; Portfolio risk reports | J21: Early warning accuracy; Limit breach incidents; Loss prevention | X21: =L21
A22: Compliance Orchestration Agent | B22: Sanctions Screening Sub-Agent | F22: SAP GTS | G22: Customer data; Sanctions lists (OFAC, UN, EU, etc.); Product/service details; Destination country | H22: Triggered on customer creation and quote validation. Screens customer names, addresses, beneficial owners against multiple sanctions lists. Uses fuzzy matching with configurable thresholds to reduce false positives. | I22: Screening results (Pass/Fail/Review); Match details with scores; Recommended actions; Audit documentation | J22: Screening time; False positive rate; Match accuracy | X22: =L22
A23: Compliance Orchestration Agent | B23: Export Control Classification Sub-Agent | F23: SAP GTS | G23: Product details; Technical specifications; Export control databases (CCL, ECCN); Destination country | H23: Triggered when products added to quote. Automatically classifies products against export control lists, determines licensing requirements, checks destination country restrictions. Flags controlled items. | I23: Product classification codes; License requirements; Export restrictions; Documentation needs | J23: Classification accuracy; Licensing compliance rate; Classification time | X23: =L23
A24: Compliance Orchestration Agent | B24: Denied Party Screening Sub-Agent | F24: SAP GTS | G24: End-user details; Intermediaries; Denied party lists (BIS, State Dept); Transaction parties | H24: Triggered during quote validation. Screens all transaction parties (buyer, end-user, intermediaries, freight forwarders) against denied party lists. Validates ownership structures for shell company risks. | I24: Party screening results; Risk assessment by party; Beneficial owner analysis; Red flag alerts | J24: Screening coverage; Hit rate accuracy; Investigation time | X24: =L24
A25: Compliance Orchestration Agent | B25: End-Use Validation Sub-Agent | F25: SAP GTS | G25: Customer declarations; Product usage patterns; Industry analysis; Historical behavior | H25: Triggered for controlled products. Analyzes declared end-use against product capabilities, customer industry, and historical patterns. Detects potential misuse risks through anomaly detection. | I25: End-use assessment (Low/Medium/High risk); Anomaly alerts; Recommended restrictions; Due diligence requirements | J25: Risk detection accuracy; Diversion prevention rate; Assessment time | X25: =L25
A26: Compliance Orchestration Agent | B26: Compliance Documentation Sub-Agent | F26: SAP GTS | G26: All screening results; Regulatory requirements; License data; Approval decisions | H26: Triggered at quote approval. Consolidates all compliance checks, generates required documentation (licenses, declarations, certificates), ensures audit trail completeness, prepares export filing data. | I26: Compliance certificate; Export documentation package; Audit trail report; Filing-ready data | J26: Documentation completeness; Audit readiness score; Generation time | X26: =L26
A27: Quote Routing & Approval Agent | B27: Deal Characteristic Analysis Sub-Agent | F27: SF CRM | G27: Quote details; Customer data; Historical deal data; Organizational rules | H27: Triggered after credit and compliance checks pass. Analyzes deal size, complexity, discount levels, risk factors, strategic importance. Scores deal on multiple dimensions to determine routing needs. | I27: Deal complexity score; Risk assessment; Strategic value rating; Routing requirements | J27: Scoring accuracy; Analysis time; Routing appropriateness | X27: =L27
A28: Quote Routing & Approval Agent | B28: Approver Selection Sub-Agent | F28: SF CRM | G28: Deal characteristics; Approval policies; Organizational hierarchy (HRIS); Approver availability/workload | H28: Triggered after deal analysis. Determines required approvers based on policies (discount %, deal size, risk level). Considers approver availability, current workload, delegation rules. Optimizes for fastest approval. | I28: Approver list with sequence; Justification for each approver; Delegation assignments; Parallel vs. sequential routing | J28: Routing accuracy; Approval cycle time; Workload balance | X28: =L28
A29: Quote Routing & Approval Agent | B29: Approval Workflow Orchestration Sub-Agent | F29: SF CRM | G29: Approver selections; Deal justification package; SLA policies; Business calendar | H29: Triggered after approver selection. Creates workflow instances, sends notifications with context, tracks responses, manages parallel approvals, handles conditional routing based on responses, escalates overdue items. | I29: Workflow status updates; Notifications to approvers; Escalation triggers; Real-time tracking dashboard | J29: On-time approval rate; Escalation frequency; Workflow completion time | X29: =L29
A30: Quote Routing & Approval Agent | B30: Approval Decision Support Sub-Agent | F30: SF CRM | G30: Deal details; Business rules repository; Similar historical deals; Win/loss data | H30: Triggered when approver opens workflow. Provides decision support by showing comparable deals, win probability, risk factors, margin analysis. Highlights policy exceptions and suggests conditions. | I30: Decision recommendation; Comparable deal analysis; Risk/reward summary; Suggested conditions/terms | J30: Decision quality (vs. outcomes); Approver satisfaction; Information usefulness | X30: =L30
A31: Quote Routing & Approval Agent | B31: Workflow Exception Handling Sub-Agent | F31: SF CRM | G31: Workflow status; Approver responses; Rejection reasons; Policy override requests | H31: Continuously monitors workflows. Handles rejections by routing back to sales with feedback, manages policy override requests, deals with approver unavailability, executes fallback routing, logs all exceptions. | I31: Exception routing decisions; Feedback to sales team; Override approvals; Exception audit log | J31: Exception resolution time; Override approval rate; Rework cycles | X31: =L31
A32: Quote Conversion Agent | B32: Conversion Readiness Sub-Agent | F32: SF CRM | G32: Quote approval status; Lead time data; Customer PO status; Contract execution status | H32: Triggered when quote approved. Validates all prerequisites for conversion: customer acceptance received, purchase order obtained, contract signed, delivery dates confirmed. Calculates optimal conversion timing. | I32: Readiness assessment (Ready/Waiting/Blocked); Missing prerequisites list; Recommended conversion date; Risk flags | J32: Conversion success rate; Time from approval to conversion; Prerequisite completion rate | X32: =L32
... A38: Quote Conversion Agent | B38: Conversion Exception Resolution Sub-Agent | F38: SF CRM | G38: Conversion errors; Conflict details; Resolution rules; Historical resolution patterns | H38: Triggered on conversion failures. Analyzes error types, attempts auto-resolution for known issues, enriches missing data where possible. Routes complex exceptions to appropriate teams with context and recommendations. | I38: Resolution actions taken; Escalation tickets with context; Retry schedules; Resolution recommendations | J38: Auto-resolution rate; Mean time to resolution; Escalation accuracy | X38: =L38
A39: Sales Enablement Agent | B39: Account Intelligence Summary Sub-Agent | D39: N/A | E39: Salesforce Agentforce | F39: SF CRM | G39: Customer master data (SF CRM, SAP MDG); Opportunity and quote history (SF CRM); Order and delivery history (SAP S/4HANA); Payment history and credit status (SAP S/4HANA); Support tickets and product issues (Service Cloud); Customer communications (Email, Slack); Product usage data and adoption metrics; Stakeholder mapping and org chart data; Industry news and company announcements; Competitive win/loss intelligence | H39: Triggered on-demand by sales reps (pre-call, pre-meeting) or scheduled for regular account reviews. Aggregates data from multiple systems via APIs and creates a unified view of the customer relationship. Applies natural language processing to summarize recent interactions, support issues, and sentiment trends. Identifies key stakeholders, decision-makers, and relationship strength. Highlights account health indicators (revenue trends, product adoption, support satisfaction, payment behavior). Detects risks (churn signals, competitive threats, unresolved issues) and opportunities (upsell potential, contract renewal timing, expansion triggers). Generates executive summary in natural language tailored to the sales rep's upcoming activity (call prep, QBR, proposal development). Continuously learns from rep feedback on summary usefulness. | I39: Executive account summary (2-3 paragraphs); Account health score with trend indicators; Recent activity timeline (orders, issues, communications); Key stakeholder map with relationship strength; Risk alerts (churn signals, payment issues, satisfaction drops); Opportunity highlights (upsell potential, whitespace analysis); Recommended talking points and questions for next interaction; Competitive intelligence relevant to this account; Action items requiring follow-up | J39: Time saved on account research per sales rep per week; Meeting preparation time reduction; Sales rep satisfaction with account insights; Meeting effectiveness score (rep and customer feedback); Customer engagement quality improvement; Early risk detection rate (churn prevention); Upsell/cross-sell opportunity identification accuracy; Account retention rate improvement | X39: =L39
A40: Sales Enablement Agent | B40: Sales Communication Generation Sub-Agent | D40: N/A | E40: Salesforce Agentforce | F40: SF CRM | G40: Customer profile and communication history (SF CRM); Deal context (quote details, stage, concerns, competitors); Email templates and best practice library; Previous successful communication patterns (won deals); Customer sentiment and engagement preferences; Product information and value propositions; Industry-specific messaging guidelines; Regulatory and compliance requirements for communications; Sales rep writing style and preferences; Meeting notes and action items from recent interactions | H40: Triggered when sales rep initiates email composition for specific scenarios (quote follow-up, proposal submission, meeting request, objection handling, contract negotiation, status update). Analyzes the context: customer relationship stage, recent interactions, outstanding issues, deal characteristics, and communication objective. Generates personalized email content using large language models fine-tuned on successful sales communications. Adapts tone based on customer seniority, industry, relationship maturity, and cultural context. Incorporates relevant data points (quote details, pricing, delivery dates) automatically from CRM. Suggests optimal subject lines based on open rate data. Provides multiple variants with different approaches (consultative, urgent, value-focused). Ensures compliance with industry regulations and company policies. Learns from rep edits and email performance (opens, responses, conversions) to improve future generations. | I40: Personalized email draft with multiple variants; Optimized subject line suggestions with predicted open rates; Tone and style recommendations based on context; Suggested call-to-action and next steps; Attachment recommendations (proposals, case studies, ROI calculators); Optimal send time prediction; Compliance check results (regulatory, legal, brand); Follow-up reminder schedule; A/B testing suggestions for important communications | J40: Email composition time reduction per sales rep; Email open rate improvement; Email response rate improvement; Meeting acceptance rate (for meeting requests); Quote acceptance rate (for proposal emails); Communication consistency across sales team; Sales rep adoption rate of generated content; Customer satisfaction with sales communications; Conversion rate by communication type; Time saved on email writing per week (team-wide) | X40: =L40
A41: Sales Enablement Agent | B41: Deal Status Intelligence Sub-Agent | D41: N/A | E41: Salesforce Agentforce | F41: SF CRM | G41: Quote data and status (SF CPQ); Approval workflow status (SF CRM); SAP order data (SAP S/4HANA); Production and fulfillment status (SAP); Shipping and delivery tracking (Logistics systems); Payment and invoicing status (SAP FI); Customer acceptance and signatures (DocuSign, Adobe Sign); Support tickets related to the deal (Service Cloud); Customer engagement data (quote views, portal activity); Historical timeline of all deal activities | H41: Triggered on-demand when sales rep views an opportunity, quote, or order, or scheduled for proactive status updates. Orchestrates API calls to multiple systems (SF CPQ, SF CRM, SAP S/4HANA, logistics, payment) to gather current status from each stage of the quote-to-cash process. Applies business logic to determine overall deal health and progress. Creates a unified timeline view showing all activities, approvals, order creation, production milestones, shipping events, and payment status. Uses natural language generation to create executive summary of where the deal stands. Identifies bottlenecks, delays, or risks (e.g., stuck in approval, production delayed, payment overdue). Highlights required actions and next steps for the sales rep. Provides customer-facing status that can be shared externally. Maintains historical snapshots for trend analysis and predictive insights on deal velocity. | I41: Unified deal status dashboard with visual timeline; Executive summary in natural language (current status, next steps); Stage-by-stage progress tracker (Quote → Approval → Order → Production → Delivery → Payment); Blocker and risk alerts with recommended actions; Expected completion dates for each pending stage; Customer-facing status summary (shareable); Historical activity log with all events and changes; Proactive notifications when status changes or issues arise; Comparison to similar deals (velocity benchmarking) | J41: Time saved on status inquiries per sales rep per week; Reduction in 'Where is my order?' customer inquiries; Deal cycle time visibility and predictability improvement; Proactive issue identification rate (before customer complaint); Sales rep satisfaction with deal visibility; Customer satisfaction with transparency and communication; Reduction in deals lost due to poor communication or delays; Forecast accuracy improvement through better visibility | X41: =L41
A42: Revenue Cloud Agent | B42: Subscription Management Sub-Agent | D42: N/A | E42: Salesforce Agentforce | F42: SF Revenue Cloud | G42: Subscription data (SF Revenue Cloud); Customer usage and consumption data; Contract terms and renewal dates; Customer engagement and product adoption metrics; Pricing and discount rules; Customer health score (CSM data); Historical renewal and churn patterns; Competitive intelligence and market pricing; Customer support ticket trends; Payment history and credit status | H42: Triggered by subscription lifecycle events (approaching renewal, usage threshold breach, contract anniversary, customer-initiated change request) or runs scheduled jobs for proactive management. Monitors subscription health by analyzing usage patterns, engagement metrics, and support interactions. Predicts renewal likelihood using ML models trained on historical churn data. For renewals, generates optimized renewal quotes considering usage trends, market pricing, competitive positioning, and customer health. For upgrades/downgrades, validates requested changes against usage patterns and recommends optimal tier. Automates routine subscription modifications (seat additions, usage adjustments) within defined parameters. For at-risk renewals, triggers proactive outreach with retention offers. Manages subscription amendments by validating pricing, proration calculations, and contract term impacts. Handles subscription consolidation for customers with multiple contracts. Ensures revenue recognition alignment with subscription changes. | I42: Renewal recommendations with optimized pricing; Churn risk alerts with retention strategies; Upsell/downsell recommendations based on usage; Automated subscription modifications (within policy); Prorated pricing calculations for mid-term changes; Contract consolidation suggestions; Renewal forecast with probability scores; Customer engagement playbooks for renewals; Revenue impact analysis for subscription changes | J42: Subscription renewal rate improvement; Net revenue retention (NRR) increase; Churn rate reduction; Time to process subscription changes; Upsell conversion rate from usage-based recommendations; Customer lifetime value (CLV) improvement; Subscription management operational efficiency; Revenue leakage reduction (pricing errors, missed renewals) | X42: =L42
A43: Revenue Cloud Agent | B43: Revenue Recognition Sub-Agent | D43: N/A | E43: Salesforce Agentforce | F43: SF Revenue Cloud | G43: Contract terms and revenue schedules (SF Revenue Cloud); Order and fulfillment data (SAP S/4HANA); Service delivery milestones and acceptance; Accounting standards and policies (ASC 606, IFRS 15); Performance obligations and deliverables; Stand-alone selling prices (SSP); Contract modifications and amendments; Variable consideration and constraints; Multi-element arrangement rules; Revenue allocation policies | H43: Triggered when new orders are created, contracts are signed, or delivery milestones are achieved. Analyzes contract terms to identify distinct performance obligations (products, services, subscriptions). Determines transaction price including variable consideration, discounts, and financing components. Allocates transaction price to performance obligations based on stand-alone selling prices using waterfall or residual approaches. Applies revenue recognition rules based on performance obligation type (point in time vs. over time). Creates revenue schedules considering contract start dates, service periods, and delivery milestones. Handles complex scenarios: contract modifications, cancellations, refunds, and amendments. Adjusts revenue schedules dynamically as contracts change or obligations are fulfilled. Ensures compliance with ASC 606/IFRS 15 requirements including disclosure tracking. Integrates with general ledger to post revenue recognition entries automatically. Maintains audit trail of all recognition decisions and rule applications. Flags unusual scenarios or policy exceptions for accounting review. | I43: Revenue recognition schedules by performance obligation; Transaction price allocation breakdowns; Automated journal entries for revenue posting; Deferred revenue tracking and forecasts; Revenue waterfall reports (bookings to recognized revenue); Compliance validation reports (ASC 606/IFRS 15); Contract modification impact analysis; Exception alerts requiring accounting review; Revenue disclosure data for financial reporting | J43: Revenue recognition cycle time (order to recognition); Manual accounting interventions (reduction); Audit finding rate related to revenue recognition; Revenue forecast accuracy improvement; Deferred revenue accuracy and predictability; Month-end close time reduction; Compliance adherence rate (ASC 606/IFRS 15); Revenue restatement incidents (reduction) | X43: =L43
A44: Revenue Cloud Agent | B44: Contract Amendment Sub-Agent | D44: N/A | E44: Salesforce Agentforce | F44: SF Revenue Cloud | G44: Original contract terms (SF Revenue Cloud); Amendment request details (scope, pricing, timing); Current revenue recognition schedules; Historical amendment patterns and approvals; Pricing and discount policies; Customer relationship and contract history; Legal and compliance requirements; Approval authority matrix; Revenue impact modeling rules; Contract change risk factors | H44: Triggered when customer or sales rep initiates contract change request (add products, change quantities, adjust pricing, extend/reduce term, modify service levels). Validates amendment request against contract terms, identifying restrictions or penalties. Calculates financial impact including proration, credit adjustments, new pricing, and term extensions. Determines whether amendment is treated as contract modification (cumulative catch-up) or new contract under revenue recognition rules. Recalculates revenue schedules considering remaining performance obligations and new transaction price. Evaluates amendment against business policies (discount thresholds, approval requirements, margin targets). Generates amendment quote with all pricing, credits, and term adjustments pre-filled. Routes for appropriate approvals based on financial impact and policy exceptions. Creates amendment documentation with clear explanation of changes and customer impact. Updates all related systems (billing, revenue recognition, order management) upon approval. Maintains version control and audit trail of all contract changes. Flags risky amendments (significant revenue reduction, unusual terms) for additional review. | I44: Amendment impact analysis (financial, revenue recognition, legal); Automated amendment quote with all adjustments; Proration and credit calculations; Updated revenue recognition schedules; Approval routing with justification package; Amendment documentation (customer-facing and internal); Risk assessment and compliance validation; System update coordination across platforms; Version-controlled contract history | J44: Amendment processing time (reduction); Amendment error rate (pricing, proration, revenue impact); Customer satisfaction with amendment process; Revenue leakage from amendment errors (reduction); Amendment approval cycle time; Self-service amendment success rate; Contract compliance with amendment policies; Amendment-related revenue restatements (reduction) | X44: =L44
A45: Experience Cloud Agent | B45: Customer Portal Self-Service Sub-Agent | D45: N/A | E45: Salesforce Agentforce | F45: SF Experience Cloud | G45: Customer account data (SF CRM); Order and delivery status (SAP S/4HANA); Product catalog and pricing (SF CPQ); Support case history (Service Cloud); Knowledge base and documentation; Invoice and payment data (SAP FI); User behavior and portal analytics; Customer preferences and permissions; Contract and entitlement data; Customer intent signals and query patterns | H45: Operates within customer-facing Experience Cloud portal, triggered by customer actions or queries. Acts as intelligent virtual assistant understanding customer intent through natural language processing. For order status inquiries, retrieves real-time data from multiple systems and presents unified timeline with shipment tracking. For document requests (invoices, quotes, contracts, certificates), identifies correct documents, verifies customer entitlement, and provides secure download links. For reorder requests, analyzes purchase history, checks current pricing and availability, and generates quote automatically. For simple support inquiries, searches knowledge base and provides relevant articles with contextual recommendations. For complex issues, intelligently routes to appropriate support team with full context. Enables self-service subscription management (view usage, upgrade/downgrade within limits, update billing info). Provides personalized product recommendations based on purchase history and usage patterns. Learns from successful vs. unsuccessful self-service interactions to improve deflection rates. Escalates to human agent when confidence is low or customer explicitly requests, providing full interaction context. | I45: Conversational responses to customer queries (chat/voice); Real-time order and delivery status with tracking; Automated document retrieval and download; Self-service quote generation for reorders; Contextual knowledge article recommendations; Subscription management interface (usage, billing, upgrades); Intelligent case creation and routing (when needed); Personalized product and service recommendations; Proactive notifications (order shipped, payment due, renewal approaching) | J45: Customer self-service deflection rate; Support case volume reduction; Customer satisfaction with portal experience (CSAT, NPS); Average time to resolution for self-service inquiries; Portal adoption rate and engagement metrics; Self-service transaction completion rate; Cost per customer interaction (reduction); Reorder conversion rate through portal | X45: =L45
A46: Experience Cloud Agent | B46: Partner Onboarding Sub-Agent | D46: N/A | E46: Salesforce Agentforce | F46: SF Experience Cloud (Partner Community) | G46: Partner application data (Experience Cloud forms); Partner business information (D&B, credit bureaus); Compliance and certification requirements; Partner program tiers and benefits; Training and enablement content; Territory and product authorization rules; Legal agreements and contract templates; Partner relationship history (if existing); Reference checks and partner reputation data; Onboarding workflow and approval policies | H46: Triggered when prospective partner initiates registration through partner portal. Guides partner through structured onboarding journey with progressive disclosure of requirements. Validates partner information in real-time (company details, tax ID, business licenses) against external data sources. Performs automated compliance screening (sanctions lists, denied parties, conflict checks with existing partners). Assesses partner fit based on geographic coverage, technical capabilities, customer base, and strategic alignment. Recommends appropriate partner tier and program based on size, capabilities, and market focus. Generates customized partner agreement incorporating selected program terms, territory rights, and compensation structure. Routes for internal approvals based on partner tier and strategic importance. Orchestrates required training and certification completion, tracking progress and sending reminders. Provisions portal access, assigns territories, and configures product authorizations upon approval. Creates personalized enablement plan with onboarding milestones, training modules, and resource access. Assigns partner success manager and schedules kickoff activities. Monitors onboarding completion and flags at-risk partners who aren't progressing. | I46: Automated partner qualification assessment; Partner tier and program recommendations; Customized partner agreement generation; Compliance validation results; Onboarding workflow with milestones and tasks; Training and certification tracking dashboard; Territory and product authorization setup; Portal access provisioning; Personalized enablement plan and resources; Partner success manager assignment; Onboarding progress alerts and reminders | J46: Partner onboarding cycle time (reduction); Onboarding completion rate; Time to first partner-sourced deal; Partner satisfaction with onboarding experience; Partner ramp time to productivity; Manual onboarding task reduction; Partner retention rate (90-day, 1-year); Partner program ROI improvement | X46: =L46
A47: Experience Cloud Agent | B47: Partner Deal Registration Sub-Agent | D47: N/A | E47: Salesforce Agentforce | F47: SF Experience Cloud (Partner Community) | G47: Deal registration submission (partner portal); Partner account and tier information; Customer account data (SF CRM); Existing opportunity and pipeline data; Territory and partner assignment rules; Deal registration policies and approval criteria; Conflict detection rules (partner overlap, direct sales); Partner incentive and discount programs; Historical deal registration patterns; Customer relationship ownership data | H47: Triggered when partner submits deal registration through portal. Validates registration completeness, ensuring all required fields are provided (customer name, opportunity details, products, estimated value, timeline). Performs intelligent customer matching using fuzzy logic to identify existing customer accounts, preventing duplicate entries. Checks for conflicts with existing opportunities, other partner registrations, and direct sales activities. Evaluates partner eligibility based on territory rights, product authorizations, program tier, and certification status. Assesses deal registration against approval policies (minimum deal size, product mix, partner capability requirements). Scores deal quality using historical win rate data, customer profile, and competitive factors. For approved registrations, automatically creates protected opportunity in Salesforce with partner attribution. Assigns appropriate deal protection period based on opportunity stage and partner tier. Calculates partner discount and incentive eligibility, applying program rules automatically. Routes exceptional cases for manual review (conflicts, policy exceptions, strategic accounts). Sends real-time notifications to partner on approval status with clear next steps. Updates partner on opportunity progress and provides collaboration workspace with internal sales team. Tracks deal protection expiration and partner engagement to prevent shelf-ware registrations. | I47: Deal registration approval/rejection decision with rationale; Conflict detection results and resolution recommendations; Protected opportunity creation in Salesforce; Partner discount and incentive calculations; Deal protection period assignment; Collaboration workspace setup (partner + internal sales); Real-time status notifications to partner; Deal quality score and win probability; Required next actions for partner and sales team; Registration expiration tracking and alerts | J47: Deal registration processing time (reduction); Auto-approval rate for registrations; Partner-sourced pipeline growth; Win rate on partner-registered deals; Partner engagement and portal adoption; Conflict resolution time; Partner satisfaction with registration process; Channel revenue contribution increase; Shelf-ware registration rate (reduction) | X47: =L47
A48: Employee Agent | B48: Sales Productivity Agent | D48: N/A | E48: Salesforce Agentforce | K48: 1. Daily task prioritization and prospecting; 2. Automated opportunity and quote creation; 3. Intelligent product and discount recommendations; 4. End-to-end quote lifecycle management; 5. Transcript summarization and follow-up scheduling | X48: =L48
A49: Employee Agent | B49: Customer Retention & Insights Agent | D49: N/A | E49: Salesforce Agentforce | K49: 1. Proactive churn detection using usage and sentiment data; 2. Suggested retention actions (emails, follow-up tasks); 3. Integrated real-time knowledge and insights for sales reps (Employee Agent & ADL) | X49: =L49
A50: Employee Agent | B50: Coaching Agent | D50: N/A | E50: Salesforce Agentforce | K50: Sales Coach Agent provides real-time coaching and personalized feedback based on performance and call data | X50: =L50

Sheet Agents Siemens crit - review
H1: Agent Specification | N1: Siemens Criteria | Z1: Value x Effort
N2: Business Value Potential | P2: Cross-business Applicability | R2: Technical Complexity & Feasibility | T2: Data readiness and ACP compliance | V2: Alignment with existing initiatives | X2: User Impact & Adoption Potential | Z2: Business Value | AB2: Implementation Effort
N3: Major penalty/loss prevention and/or direct revenue/profit driver + time to value < 3 months | P3: Applicable across all business divisions with minimal customization | R3: Requires integration across multiple systems with different technologies (e.g., Salesforce + SAP + others), complex data orchestration needs | T3: Meets requirements: Use case can be implemented with ACP Level 2 or lower | V3: Complements existing initiatives, creates synergies | X3: Addresses Siemens pain point and a large user base that is employee-facing (e.g. Sales Reps) | Z3: =N3 | AB3: Requires >6 months
N4: Moderate efficiency gains and/or indirect contribution + time to value 3-6 months | P4: Widely applicable but requires some customization per business division | R4: Requires integration between 1-2 systems on similar technology (e.g., multiple Salesforce orgs), standard data requirements | T4: - | V4: No overlap, independent initiative | X4: Addresses Siemens pain point and a affects a smaller number of user or user base is customer-facing | Z4: =N4 | AB4: Requires 3-6 months
H5: Host System | I5: Input (Sources/Supplier) | J5: How does this agent technically work? | K5: Agent Output | L5: KPIs to measure business impact | M5: ACN Asset | N5: Minor savings and/or cost savings only + time to value > 6 months | P5: Limited to single business division or single use case | R5: Self-contained within one system (e.g., Salesforce), no external integrations required, aligns with existing AI standards | T5: Does not meet requirements: Requires ACP Level 3 or higher (potential blocker) | V5: Duplicates existing efforts or conflicts with current business roadmap(s) | X5: Does not address a Siemens pain point | Z5: =N5 | AB5: Can be implemented in ≤3 months
A6: Super Agent Use Case | B6: Sub-Agent Use Cases | C6: Agent Description (short) | D6: Pain Point Addressed | E6: Agent Practicality and Tech. (Does this qualify to be AI Agent use case? If yes, what is the agent tech?) | F6: Rationale for column E | G6: Used Technology | H6: What system does the agent mostly operate in | I6: What are the input sources | J6: What does the agent do, from trigger to operating mode | K6: What is the agents output | L6: How can we determine the value of each agent | N6: The agents should be able to provide quick wins and demonstrate measurable business impact, such as improved productivity, cost savings, or revenue generation. | P6: The agents should not be limited to a specific business division (e.g., DI or SI) but should be applicable across the organization. | R6: The agents should be feasible to implement within the existing technical constraints and align with Siemens' AI standards and orchestration capabilities (e.g. data cloud capabilities). | T6: The agents should not require level 3 as this would be an additional challenge (e.g. SieSales currently has ACP level 2 data). | V6: The agents should not duplicate efforts or overlap with the agent use cases already being worked on by the team. -> No overlap (no), yes there are similar use cases already worked on based on SI/DI/Agentforce use cases (yes) | X6: The agents should address the needs of a significant user base and target specific pain points or gaps in the current CRM usage. | Z6: As before based on "cost avoidance", "sales & profitability" and "time to value (months)". -> see "Business Value Potential" | AB6: Based on implementation time.
A7: Master Data Quality Agent | B7: Duplicate Detection Sub-Agent | C7: Detects when the same corporate account (company) exists multiple times in CRM/ERP by comparing company names, tax IDs, DUNS numbers, and registered addresses using similarity scoring (e.g., 'Siemens AG' vs 'Siemens A.G.' scores 95% match). Flags duplicates for merge or manual review. | D7: [Data Fragmentation & Siloed Information] Same corporate account exists 3-5 times across CRM/ERP systems with different spellings (e.g., 'BMW AG', 'BMW Group', 'Bayerische Motoren Werke'). Sales reps unknowingly compete on same account. Credit limits fragmented. Account history incomplete. | E7: Does not qualify as AI Agent | F7: RATIONALE: TECHNOLOGY: OOB: SAP MDG Duplicate Check, Salesforce Data Cloud Matching Rules | CUSTOM: MuleSoft cross-system sync EVIDENCE FROM HOST SYSTEM (SAP MDG): - SAP MDG has built-in OOB duplicate detection - Primary system is ERP, not Salesforce-native EVIDENCE FROM INPUT SOURCES: - Structured data with predefined fuzzy matching rules - No learned patterns, no ML training data specified CONCLUSION: Core functionality (fuzzy matching, similarity scoring 0-100%, auto-merge >95%, cross-system sync) is achievable with OOB tools. AI designation requires adding genuine ML (e.g., learning from data steward merge/reject decisions). | G7: OOB: SAP MDG Duplicate Check, Salesforce Data Cloud Matching Rules | CUSTOM: MuleSoft integration for cross-system deduplication workflow (sync duplicates flagged in either system) | H7: SAP MDG + Salesforce Data Cloud (OOB). MuleSoft cross-system sync (CUSTOM). | I7: Corporate account records (Salesforce CRM, SAP MDG); Company name variations; Tax IDs (VAT, DUNS); Registered addresses; Account hierarchies | J7: Triggered on new/changed corporate account records in either Salesforce or SAP MDG. SAP MDG Duplicate Check and Salesforce Data Cloud Matching Rules run similarity algorithms on company name, tax ID, address. Scores matches (0-100%). High-confidence duplicates (>95%) auto-merged; others queued for data steward review. | K7: Duplicate alerts with confidence score; Merge recommendations; Auto-merge execution (>95%); Cross-system duplicate notification via MuleSoft | L7: Duplicate record reduction rate; False positive rate (<5% target); Auto-merge accuracy; Sales rep time saved (hours/week) | N7: Low | O7: Limited direct revenue impact. Primarily operational efficiency. Consider bundling with related agents to increase value proposition. | P7: High | Q7: Master data quality affects all divisions using shared CRM/ERP systems. Duplicate accounts, address errors, and data inconsistencies impact DI, SI, and MO equally. | R7: Medium | S7: 2 system integrations required. Systems: SAP MDG, Salesforce Data Cloud, MuleSoft. Some custom development needed. Standard connectors and APIs available. | T7: High | U7: Standard CRM data. ACP Level 2 sufficient for implementation. | V7: Medium | W7: RELATED SAP SOLUTION: SAP Master Data Consistency (F18) - AVAILABLE in SAP Joule catalog, NOT DEPLOYED at Siemens. (SOURCE: SAP Joule Feature List - external, requires Siemens IT verification). SAP F18 function: Checks data consistency within S/4HANA MDG. SPECIFIC DIFFERENTIATOR: Duplicate Detection operates in SALESFORCE (Account/Contact dedup), not S/4HANA MDG. Different data sources (SFDC vs SAP), different matching algorithms. Checked: AF (12), DI (10), SI (9) - NONE address Salesforce-specific deduplication. | X7: Medium | Y7: Addresses [Data Fragmentation & Siloed Information] pain point. 'Same corporate account exists 3-5 times across CRM/ERP systems with different spellings (e...'. Moderate user impact. | Z7: Low | AA7: Limited direct revenue impact. Primarily operational efficiency. Consider bundling with related agents to increase value proposition. | AB7: High | AC7: Extended timeline: >6 months. Complex factors: SAP integration, custom development. Plan for phased rollout.
A8: Master Data Quality Agent | B8: Address Validation Sub-Agent | C8: Validates business ship-to addresses (factories, warehouses, distribution centers) and bill-to addresses (corporate headquarters, regional finance offices) against commercial postal databases. Standardizes formats, adds missing postal codes, and validates dock/bay numbers for industrial deliveries. | D8: [Data Fragmentation & Siloed Information] Ship-to and bill-to addresses stored differently across CRM, ERP, and logistics systems. Industrial shipments returned because address formats don't match carrier requirements. Missing dock numbers and building codes cause delivery failures. | E8: Does not qualify as AI Agent | F8: RATIONALE: TECHNOLOGY: OOB: SAP MDG Address Validation with SAP Address Directory, Loqate/Melissa API AI QUALIFICATION: NO - Address validation is deterministic rule-based processing - Postal database lookup, format standardization, postal code matching - Dock/bay number validation follows fixed industrial address formats - No learning, prediction, or NLP required SIEMENS CRITERIA ASSESSMENT: - Business Value: HIGH (reduces delivery failures, carrier rejections) - Cross-business Applicability: HIGH (all divisions ship products) - Technical Complexity: LOW (OOB tools available) - ACP Compliance: Level 1 (OOB configuration) - Alignment with Initiatives: MEDIUM (data quality initiative) - User Impact: MEDIUM (automatic corrections reduce manual work) CONCLUSION: Valuable functionality but OOB SAP MDG Address Validation and Salesforce validation rules are sufficient. AI adds no incremental value over existing postal database APIs. | G8: OOB: SAP MDG Address Validation with SAP Address Directory | CONFIG: Validation rules for B2B industrial addresses (dock numbers, building codes) | ALTERNATIVE: Loqate/Melissa API if SAP coverage insufficient | H8: SAP MDG (OOB). Configure B2B address rules. | I8: Ship-to addresses (factories, warehouses, DCs); Bill-to addresses (HQ, regional offices); SAP Address Directory; Loqate/Melissa API (if needed) | J8: Triggered on address creation/update in Salesforce or SAP MDG. SAP MDG Address Validation standardizes format, validates against postal databases, adds missing postal codes. For industrial addresses, validates dock numbers and building codes. Auto-corrects minor errors; flags major issues for manual review. | K8: Validated addresses with standardized format; Correction suggestions; Validation status (Valid/Invalid/Corrected); Industrial location details (dock, bay) | L8: Delivery failure reduction %; Address validation success rate; Auto-correction rate; Reshipment cost savings (€) | N8: High | O8: Strong business impact based on operational efficiency gains. Addresses [Data Fragmentation & Siloed Information] pain point with measurable ROI. | P8: High | Q8: Master data quality affects all divisions using shared CRM/ERP systems. Duplicate accounts, address errors, and data inconsistencies impact DI, SI, and MO equally. | R8: Medium | S8: 1 system integration required. Systems: SAP MDG. Standard connectors and APIs available. | T8: High | U8: Standard CRM data. ACP Level 2 sufficient for implementation. | V8: Medium | W8: RELATED SAP SOLUTION: SAP Master Data Consistency (F18) - AVAILABLE in SAP Joule catalog, NOT DEPLOYED at Siemens. (SOURCE: SAP Joule Feature List - external). SPECIFIC DIFFERENTIATOR: Address Validation integrates with EXTERNAL services (USPS, Google Maps API, Loqate) for Salesforce addresses. F18 validates within SAP MDG only. Checked: AF (12), DI (10), SI (9) - NONE address Salesforce address validation. | X8: High | Y8: Addresses critical pain: [Data Fragmentation & Siloed Information]. Specific issue: 'Ship-to and bill-to addresses stored differently across CRM, ERP, and logistics systems...'. Quantified impact in source data. | Z8: High | AA8: Strong business impact based on operational efficiency gains. Addresses [Data Fragmentation & Siloed Information] pain point with measurable ROI. | AB8: Medium | AC8: Standard timeline: 3-6 months. 1 system integration. Key systems: SAP MDG.
A9: Master Data Quality Agent | B9: Data Completeness Sub-Agent | C9: Checks corporate account records for missing mandatory fields required by business segment (e.g., manufacturing accounts need plant codes; distribution accounts need warehouse IDs). Calculates completeness score (0-100%) and triggers data steward workflows when critical fields are empty. | D9: [Data Fragmentation & Siloed Information] Corporate account records missing critical fields across systems (tax ID in CRM, payment terms in ERP, industry code in MDM). Downstream processes blocked. Sales reps waste 2-3 hours per deal hunting for data scattered across systems. | E9: Does not qualify as AI Agent | F9: RATIONALE: TECHNOLOGY: OOB: SAP MDG Data Quality Rules, Salesforce Validation Rules AI QUALIFICATION: NO - Completeness checking is deterministic (field present/missing) - Scoring is simple calculation (filled fields / required fields × 100) - Business segment rules are configured, not learned - Workflow triggers follow fixed thresholds SIEMENS CRITERIA ASSESSMENT: - Business Value: HIGH (prevents downstream process blocks) - Cross-business Applicability: HIGH (all divisions need complete data) - Technical Complexity: LOW (OOB validation rules) - ACP Compliance: Level 1 (OOB configuration) - Alignment with Initiatives: HIGH (data quality initiative) - User Impact: HIGH (saves 2-3 hours per deal on data hunting) CONCLUSION: High-value data quality function but purely rule-based. OOB SAP MDG Data Quality Rules and Salesforce Validation Rules fully address this need without AI. | G9: OOB: SAP MDG Data Quality Rules, Salesforce Validation Rules | CONFIG: Define mandatory fields per business segment (manufacturing needs plant codes, distribution needs warehouse IDs) | H9: SAP MDG + Salesforce (OOB). Configure segment-specific rules. | I9: Corporate account master records (SAP MDG); Required field definitions by business segment; Segment rules (manufacturing, distribution, service) | J9: Triggered on record save in Salesforce or SAP MDG. SAP MDG Data Quality Rules evaluate completeness based on account segment (manufacturing accounts need plant codes; distribution needs warehouse IDs). Calculates completeness score (0-100%). Triggers data steward workflow when critical fields missing. | K9: Completeness score (0-100%); Missing critical fields list; Priority ranking by business impact; Data steward task queue | L9: Overall completeness score improvement; Critical field completion rate (>95% target); Time to complete records; Blocked quotes due to missing data | N9: High | O9: Strong business impact with quantified targets: >95%. Addresses [Data Fragmentation & Siloed Information] pain point with measurable ROI. | P9: High | Q9: Master data quality affects all divisions using shared CRM/ERP systems. Duplicate accounts, address errors, and data inconsistencies impact DI, SI, and MO equally. | R9: Medium | S9: 2 system integrations required. Systems: SAP MDG. Standard connectors and APIs available. | T9: High | U9: Standard CRM data. ACP Level 2 sufficient for implementation. | V9: Medium | W9: RELATED SAP SOLUTION: SAP Master Data Consistency (F18) - AVAILABLE in SAP Joule catalog, NOT DEPLOYED at Siemens. (SOURCE: SAP Joule Feature List - external). SPECIFIC DIFFERENTIATOR: Data Completeness enforces SALESFORCE-specific required fields (custom objects, SieSales picklists, validation rules). F18 addresses S/4HANA MDG fields only. Checked: AF (12), DI (10), SI (9) - NONE address Salesforce data completeness. | X9: High | Y9: Addresses critical pain: [Data Fragmentation & Siloed Information]. Specific issue: 'Corporate account records missing critical fields across systems (tax ID in CRM, payment terms in ERP, industry code in ...'. Quantified impact in source data. | Z9: High | AA9: Strong business impact with quantified targets: >95%. Addresses [Data Fragmentation & Siloed Information] pain point with measurable ROI. | AB9: Medium | AC9: Standard timeline: 3-6 months. 2 system integrations. Key systems: SAP MDG.
A10: Master Data Quality Agent | B10: Data Consistency Sub-Agent | C10: Compares corporate account data across CRM, ERP, and CPQ systems to detect mismatches (e.g., credit limit is €500K in Salesforce but €300K in SAP). Identifies which system has the correct value based on update timestamps and data governance rules. | D10: [Data Fragmentation & Siloed Information] Same corporate account has different values across systems: credit limit €500K in Salesforce vs €300K in SAP. Payment terms 'Net 30' in CRM vs 'Net 60' in ERP. No single source of truth. 5-10 hours per week spent reconciling. | E10: Does not qualify as AI Agent | F10: RATIONALE: TECHNOLOGY: CUSTOM: MuleSoft cross-system data reconciliation AI QUALIFICATION: NO - Cross-system comparison is deterministic (value A ≠ value B) - Golden source resolution follows explicit business rules (e.g., SAP MDG is master) - Conflict detection compares timestamps and data governance rules - No pattern learning, prediction, or NLP involved SIEMENS CRITERIA ASSESSMENT: - Business Value: HIGH (saves 5-10 hours/week on reconciliation) - Cross-business Applicability: HIGH (all divisions have CRM/ERP data) - Technical Complexity: MEDIUM (custom MuleSoft integration required) - ACP Compliance: Level 2 (custom integration, no AI) - Alignment with Initiatives: HIGH (integration platform initiative) - User Impact: HIGH (single source of truth) CONCLUSION: Requires custom MuleSoft development but logic is deterministic. Integration work, not AI work. Valuable but mislabeled as "agent". | G10: CUSTOM: MuleSoft cross-system data reconciliation (no OOB product compares data across CRM/ERP/CPQ). Build event-driven sync with conflict detection and golden source resolution. | H10: MuleSoft (CUSTOM). No OOB solution exists. | I10: Corporate account data from Salesforce CRM, SAP MDG, SAP S/4HANA; Cross-reference rules; Golden source definitions | J10: Triggered on sync events via MuleSoft. Custom reconciliation logic compares corporate account data across systems (credit limit, payment terms, account hierarchy). Detects mismatches. Applies golden source resolution rules (SAP MDG is master for customer data). Flags conflicts for manual resolution. | K10: Consistency violation reports; Auto-reconciliation actions; Conflict details with source comparison; Golden source update triggers | L10: Data consistency score across systems; Cross-system sync errors per week; Reconciliation time (hours saved); Invoice dispute reduction | N10: Low | O10: Limited direct revenue impact. Primarily operational efficiency. Consider bundling with related agents to increase value proposition. | P10: High | Q10: Master data quality affects all divisions using shared CRM/ERP systems. Duplicate accounts, address errors, and data inconsistencies impact DI, SI, and MO equally. | R10: Medium | S10: 1 system integration required. Systems: MuleSoft. Some custom development needed. Standard connectors and APIs available. | T10: High | U10: Standard CRM data. ACP Level 2 sufficient for implementation. | V10: Medium | W10: RELATED SAP SOLUTION: SAP Master Data Consistency (F18) - AVAILABLE in SAP Joule catalog, NOT DEPLOYED at Siemens. (SOURCE: SAP Joule Feature List - external). SPECIFIC DIFFERENTIATOR: Data Consistency validates CROSS-SYSTEM integrity (SFDC Account = SAP Customer, SFDC Product = SAP Material). F18 is SAP-internal only. Checked: AF (12), DI (10), SI (9) - NONE address cross-system data consistency. | X10: High | Y10: Addresses critical pain: [Data Fragmentation & Siloed Information]. Specific issue: 'Same corporate account has different values across systems: credit limit €500K in Salesforce vs €300K in SAP...'. Quantified impact in source data. | Z10: Low | AA10: Limited direct revenue impact. Primarily operational efficiency. Consider bundling with related agents to increase value proposition. | AB10: High | AC10: Extended timeline: >6 months. Complex factors: custom development. Plan for phased rollout.
A11: Master Data Quality Agent | B11: Data Change Monitoring Sub-Agent | C11: Monitors all changes to corporate account master data (credit limits, payment terms, account hierarchies, legal entity names) and maintains audit trail. Alerts data stewards when unusual patterns occur (e.g., 50 accounts modified by same user in 1 hour). | D11: [Data Fragmentation & Siloed Information] Changes to master data across systems not tracked centrally. Cannot trace who changed credit limits, payment terms, or account hierarchies. Audit failures from missing documentation. Data lineage unknown. | E11: Does not qualify as AI Agent | F11: RATIONALE: TECHNOLOGY: OOB: SAP MDG Change Documents, Salesforce Shield Event Monitoring AI QUALIFICATION: NO - Change logging is built into both platforms - Anomaly detection uses configured thresholds (e.g., >50 changes/hour) - Pattern rules are predefined, not learned from data - Audit trail is standard platform capability SIEMENS CRITERIA ASSESSMENT: - Business Value: HIGH (SOX compliance, audit readiness) - Cross-business Applicability: HIGH (all divisions need audit trails) - Technical Complexity: LOW (OOB with configuration) - ACP Compliance: Level 1 (OOB features) - Alignment with Initiatives: HIGH (compliance initiative) - User Impact: MEDIUM (data steward alerts) CONCLUSION: Critical for compliance but fully addressed by OOB capabilities. SAP MDG Change Documents and Salesforce Shield provide exactly this functionality without AI. | G11: OOB: SAP MDG Change Documents, Salesforce Shield Event Monitoring | CONFIG: Alert rules for suspicious patterns (bulk changes, unauthorized users, off-hours modifications) | H11: SAP MDG + Salesforce Shield (OOB). Configure alert thresholds. | I11: Change logs from SAP MDG and Salesforce Shield; Audit rules; Suspicious pattern definitions (bulk changes, off-hours, unauthorized users) | J11: Continuously monitors via SAP MDG Change Documents and Salesforce Shield Event Monitoring. Detects anomalous patterns (50+ accounts modified by same user, credit limit changes outside business hours). Triggers alerts. Maintains SOX-compliant audit trail. | K11: Change history reports; Anomaly alerts with pattern details; Audit documentation for SOX compliance; Rollback recommendations | L11: Anomaly detection rate; Audit compliance score (100% target); Mean time to detect unauthorized changes; SOX audit findings reduction | N11: High | O11: Strong business impact with quantified targets: 100%. Addresses [Data Fragmentation & Siloed Information] pain point with measurable ROI. | P11: High | Q11: Master data quality affects all divisions using shared CRM/ERP systems. Duplicate accounts, address errors, and data inconsistencies impact DI, SI, and MO equally. | R11: Medium | S11: 2 system integrations required. Systems: SAP MDG. Standard connectors and APIs available. | T11: High | U11: Standard CRM data. ACP Level 2 sufficient for implementation. | V11: Medium | W11: RELATED SAP SOLUTION: SAP Master Data Consistency (F18) - AVAILABLE in SAP Joule catalog, NOT DEPLOYED at Siemens. (SOURCE: SAP Joule Feature List - external). SPECIFIC DIFFERENTIATOR: Data Change Monitoring tracks SALESFORCE field changes in real-time using Platform Events. F18 monitors S/4HANA MDG changes only. Checked: AF (12), DI (10), SI (9) - NONE address Salesforce change tracking. | X11: High | Y11: Addresses critical pain: [Data Fragmentation & Siloed Information]. Specific issue: 'Changes to master data across systems not tracked centrally...'. Quantified impact in source data. | Z11: High | AA11: Strong business impact with quantified targets: 100%. Addresses [Data Fragmentation & Siloed Information] pain point with measurable ROI. | AB11: Medium | AC11: Standard timeline: 3-6 months. 2 system integrations. Key systems: SAP MDG.
A12: Master Data Quality Agent | B12: Data Enrichment Sub-Agent | C12: Retrieves firmographic data from Dun & Bradstreet (D&B) for corporate accounts: annual revenue, employee count, industry codes (SIC/NAICS), corporate hierarchy (parent/subsidiary relationships), and headquarters location. Fills gaps in account profiles to enable accurate segmentation. | D12: [Data Fragmentation & Siloed Information] Firmographic data (revenue, employees, industry, parent company) incomplete or missing. Cannot segment corporate accounts accurately. Credit and sales decisions based on fragmented, outdated information or requirement to check in multiple systems. | E12: Does not qualify as AI Agent | F12: RATIONALE: TECHNOLOGY: OOB: Salesforce Data Cloud + D&B Connect API AI QUALIFICATION: NO - D&B data retrieval is API lookup, not AI - Data enrichment is deterministic field population - Firmographic matching uses database queries, not ML - "Agentforce Employee Agent assists reps with enrichment queries" = chat interface over database lookup - Chat interface does not transform rule-based lookup into AI agent EVIDENCE FROM TECHNICAL OPERATION: - Trigger: New account or data gap detected - Process: API call to D&B → field mapping → record update - No learning, no prediction, no autonomous decision-making SIEMENS CRITERIA ASSESSMENT: - Business Value: HIGH (data completeness) - Cross-business Applicability: HIGH (all accounts) - Technical Complexity: LOW (OOB integration) - ACP Compliance: Level 1 (OOB) - Alignment with Initiatives: MEDIUM - User Impact: MEDIUM CONCLUSION: This is data integration with a conversational UI, not an AI agent. The intelligence is in D&B's data, not in any Siemens-trained model. | G12: OOB: Salesforce Data Cloud with D&B Connect (AppExchange package) | CONFIG: Map D&B fields to Siemens account segments | AGENTFORCE: Employee Agent assists reps with enrichment queries | H12: Salesforce Data Cloud + D&B Connect (OOB). Agentforce Employee Agent (OOB). | I12: Corporate account records from Salesforce CRM; D&B Connect API; Firmographic data (revenue, employees, industry, parent company); Agentforce Employee Agent queries | J12: Triggered on new account creation or when Data Completeness Sub-Agent identifies gaps. Salesforce Data Cloud with D&B Connect retrieves firmographic data. Agentforce Employee Agent assists sales reps with enrichment queries. Validates data quality, merges with existing records. Weekly batch enrichment for currency. | K12: Enriched corporate account profiles; Firmographic data (revenue, employees, NAICS/SIC); Corporate hierarchy (parent/subsidiaries); Confidence scores; Data freshness timestamps | L12: Field fill rate improvement %; Enrichment match rate; Account segmentation accuracy; Credit decision accuracy lift | N12: Low | O12: Limited direct revenue impact. Primarily operational efficiency. Consider bundling with related agents to increase value proposition. | P12: High | Q12: Master data quality affects all divisions using shared CRM/ERP systems. Duplicate accounts, address errors, and data inconsistencies impact DI, SI, and MO equally. | R12: Medium | S12: 2 system integrations required. Systems: Salesforce Data Cloud, Agentforce Employee Agent. Standard connectors and APIs available. | T12: High | U12: Standard CRM data. ACP Level 2 sufficient for implementation. | V12: Medium | W12: RELATED BUT DIFFERENT FUNCTION: SieSales Employee Agent (AF Tab Row 7, IN IMPLEMENTATION) SUMMARIZES existing CRM records. This agent ENRICHES with EXTERNAL data from D&B (firmographics, revenue, employee count, corporate hierarchy). Different functions: Summarization of internal data vs Addition of external data. HOWEVER: Row 12 description mentions 'Agentforce Employee Agent assists reps with enrichment queries' - so there IS integration touchpoint. STATUS: MEDIUM - not direct conflict but coordinate with Customer 360 team on data model alignment. RECOMMENDATION: Ensure D&B enriched fields feed into Customer 360 summaries. | X12: High | Y12: Addresses critical pain: [Data Fragmentation & Siloed Information]. Specific issue: 'Firmographic data (revenue, employees, industry, parent company) incomplete or missing...'. Quantified impact in source data. | Z12: Low | AA12: Limited direct revenue impact. Primarily operational efficiency. Consider bundling with related agents to increase value proposition. | AB12: Low | AC12: Quick win: ≤3 months. Primarily OOB configuration. Systems: Salesforce Data Cloud, Agentforce Employee Agent. Minimal dependencies.
A13: Quote Configuration Agent | B13: Product Recommendation Sub-Agent | C13: Analyzes what products a corporate account has purchased historically, their industry vertical, and company size to suggest relevant additional products. Example: A manufacturing account buying PLCs likely needs HMI panels and industrial networking equipment. | D13: [Information Overload & Decision Paralysis] Sales reps overwhelmed by 10,000+ SKU product catalog. Cannot identify which products fit corporate account's needs. No intelligent navigation through complex industrial portfolios. Decision paralysis leads to suboptimal recommendations. | E13: Qualifies - Salesforce Agentforce Sales | F13: RATIONALE: TECHNOLOGY: OOB: Salesforce Einstein Recommendation Builder + Agentforce Sales Agent AI QUALIFICATION: YES - Einstein Recommendation Builder uses ML to analyze purchase history, industry vertical, company size - Agentforce Sales Agent delivers recommendations with NLP conversational interface - Pattern recognition across 10,000+ SKU catalog - Model learns from sales outcomes SIEMENS CRITERIA ASSESSMENT: - Business Value: HIGH (addresses 10,000+ SKU decision paralysis) - Cross-business Applicability: HIGH (all sales divisions) - Technical Complexity: LOW (OOB Salesforce platform) - ACP Compliance: Level 1 (OOB Einstein + Agentforce) - Alignment with Initiatives: HIGH (Salesforce Einstein initiative) - User Impact: HIGH (intelligent catalog navigation) PLATFORM FIT: Salesforce Agentforce Sales Agent + Einstein - Pre-built AI capabilities - Trained on Siemens catalog and history - No custom AI development required CONCLUSION: Genuine AI use case with OOB platform agents. Use Salesforce Agentforce Sales + Einstein Recommendation Builder. | G13: OOB: Salesforce Einstein Recommendation Builder | CONFIG: Train model on Siemens product catalog, purchase history, installed base | AGENTFORCE: Sales Agent delivers recommendations to reps | H13: Salesforce Einstein + Agentforce Sales Agent (OOB). Configure recommendation model. | I13: Corporate account profile and purchase history; Installed base data (from SAP); Product catalog (10,000+ SKUs); Agentforce Sales Agent context | J13: Triggered when quote initiated. Salesforce Einstein Recommendation Builder analyzes corporate account industry, size, purchase history, installed base. Agentforce Sales Agent delivers ranked product recommendations to sales rep. Considers margin optimization and inventory availability. | K13: Recommended products ranked by fit score; Bundle suggestions; Alternative options; Recommendation rationale for sales rep | L13: Recommendation acceptance rate; Upsell success rate; Quote value increase %; Sales rep time saved on product selection | M13: Salesforce Agentforce (Employee Agent) recommends the most suitable products and optimal discounts by analyzing customer needs and past sales. | N13: Low | O13: Limited direct revenue impact. Primarily operational efficiency. Consider bundling with related agents to increase value proposition. | P13: High | Q13: Quote and pricing processes are standardized across Siemens divisions. CPQ rules and approval workflows apply to DI, SI, and MO sales teams. | R13: Medium | S13: 2 system integrations required. Systems: Agentforce Sales Agent. Standard connectors and APIs available. | T13: High | U13: Standard CRM data. ACP Level 2 sufficient for implementation. | V13: Low | W13: FUTURE INITIATIVE ONLY: Product recommendations relate to Quoting Agent. Checked: AF (12), DI (10), SI (9) - NONE provide ML-based product recommendations today. Quoting Agent STATUS: 'In discussion, not until May' (AF Tab Row 8). DI #4 Quoting Agent is same initiative - predefined logic, not ML recommendations. RECOMMENDATION: Proceed - no current conflict, design for future Quoting Agent integration. | X13: Medium | Y13: Addresses [Information Overload & Decision Paralysis] pain point. 'Sales reps overwhelmed by 10,000+ SKU product catalog...'. Moderate user impact. | Z13: Low | AA13: Limited direct revenue impact. Primarily operational efficiency. Consider bundling with related agents to increase value proposition. | AB13: Medium | AC13: Standard timeline: 3-6 months. 2 system integrations. Key systems: Agentforce Sales Agent.
A14: Quote Configuration Agent | B14: Pricing Optimization Sub-Agent | C14: Calculates optimal pricing for each corporate account based on: negotiated contract rates, volume commitment tiers, customer segment (strategic/key/standard), competitive bid situations, and target margin thresholds. Recommends discount percentages that maximize win probability while protecting margins. | D14: [Manual, Time-Intensive Processes] Pricing calculations done manually in spreadsheets: 2-4 hours per complex quote. Discount approvals via email chains. No systematic margin analysis. Inconsistent pricing across channels - same account gets different prices from different reps. | E14: Qualifies - Salesforce Agentforce Quoting | F14: RATIONALE: TECHNOLOGY: OOB: Agentforce Quoting Agent (Siemens planned May 2025) + Salesforce Revenue Cloud AI QUALIFICATION: YES - Agentforce Quoting Agent is Salesforce's AI-powered pricing optimization - Learns from historical win/loss data to optimize pricing - Considers competitive dynamics, customer segment, margin targets - AI-driven discount recommendations SIEMENS CRITERIA ASSESSMENT: - Business Value: HIGH (saves 2-4 hours per complex quote) - Cross-business Applicability: HIGH (all divisions quote products) - Technical Complexity: LOW (OOB Agentforce + Revenue Cloud) - ACP Compliance: Level 1 (OOB Salesforce platform) - Alignment with Initiatives: HIGH (CPQ modernization, AI adoption) - User Impact: HIGH (eliminates spreadsheet pricing) PLATFORM FIT: Salesforce Agentforce Quoting Agent - AI-native pricing optimization - Integrates with Revenue Cloud pricing rules - Siemens already planning May 2025 rollout CONCLUSION: Genuine AI use case. Agentforce Quoting Agent provides AI-powered pricing optimization OOB. | G14: OOB: Agentforce Quoting Agent (Siemens planned May 2025), Salesforce Revenue Cloud | CONFIG: Define pricing rules, margin thresholds, discount approval limits per segment/region | H14: Agentforce Quoting Agent + Revenue Cloud (OOB). Configure pricing rules. | I14: Product selections; Pricing rules and matrices (Revenue Cloud); Contract rates; Volume tiers; Competitive bid data; Margin thresholds | J14: Triggered after product selection. Agentforce Quoting Agent with Salesforce Revenue Cloud calculates optimal pricing. Considers negotiated contract rates, volume commitment tiers, customer segment (strategic/key/standard), target margins. Suggests discount levels, validates against approval thresholds. | K14: Optimized pricing per line item; Discount recommendations with rationale; Margin analysis; Approval requirements triggered; Competitive positioning guidance | L14: Win rate by pricing tier; Margin realization vs. target; Discount variance from policy; Pricing calculation time (minutes saved) | M14: Salesforce Agentforce (Employee Agent) recommends the most suitable products and optimal discounts by analyzing customer needs and past sales. | N14: High | O14: Strong business impact based on operational efficiency gains. Addresses [Manual, Time-Intensive Processes] pain point with measurable ROI. | P14: High | Q14: Quote and pricing processes are standardized across Siemens divisions. CPQ rules and approval workflows apply to DI, SI, and MO sales teams. | R14: Medium | S14: 2 system integrations required. Systems: Agentforce Quoting Agent. Standard connectors and APIs available. | T14: Low | U14: ⚠️ POTENTIAL BLOCKER: May require ACP Level 3 due to sensitive data access. | V14: Low | W14: FUTURE INITIATIVE ONLY: Pricing relates to Quoting Agent. Checked: AF Row 8 (DISCUSSION), DI #4 (predefined) - same initiative, not built. No live pricing optimization exists. RECOMMENDATION: Proceed. Design for future CPQ integration. | X14: High | Y14: Addresses critical pain: [Manual, Time-Intensive Processes]. Specific issue: 'Pricing calculations done manually in spreadsheets: 2-4 hours per complex quote...'. Quantified impact in source data. | Z14: High | AA14: Strong business impact based on operational efficiency gains. Addresses [Manual, Time-Intensive Processes] pain point with measurable ROI. | AB14: Low | AC14: Quick win: ≤3 months. Primarily OOB configuration. Systems: Agentforce Quoting Agent. Minimal dependencies.
A15: Quote Configuration Agent | B15: Technical Feasibility Sub-Agent | C15: Validates that selected product combinations are technically compatible for the customer's installation environment. Example: Checks that a 480V motor controller is compatible with customer's 480V power supply, not mismatched with 230V equipment. | D15: [Inconsistent & Low-Quality Customer Interactions] Incompatible product configurations quoted to corporate accounts: 480V equipment for 230V facility, wrong software versions, missing required accessories. Inconsistent technical validation leads to order cancellations and engineering rework. | E15: Does not qualify as AI Agent | F15: RATIONALE: TECHNOLOGY: OOB: Salesforce CPQ Configuration Rules Engine + Custom Apex AI QUALIFICATION: NO - Compatibility checking is deterministic (480V ≠ 230V) - Rules are explicit engineering constraints, not learned patterns - Software version matching follows fixed compatibility matrices - No prediction, learning, or NLP involved SIEMENS CRITERIA ASSESSMENT: - Business Value: HIGH (prevents incompatible configurations) - Cross-business Applicability: HIGH (all product divisions) - Technical Complexity: MEDIUM (CPQ rules + some custom Apex) - ACP Compliance: Level 2 (OOB CPQ + custom Apex) - Alignment with Initiatives: MEDIUM (CPQ implementation) - User Impact: HIGH (reduces engineering rework) CONCLUSION: Critical functionality but purely rule-based. CPQ Configuration Rules Engine executes deterministic constraints. No AI required - just well-defined engineering compatibility rules. | G15: OOB: Salesforce CPQ Configuration Rules Engine | CONFIG: Define compatibility rules (voltage, software versions, required accessories) | CUSTOM: Complex technical validation may need Apex for edge cases | H15: Salesforce CPQ (OOB). CUSTOM Apex for complex compatibility logic. | I15: Product configurations; Technical compatibility rules (voltage, software versions); Engineering constraints from PLM; Corporate account installation environment data | J15: Triggered during configuration. Salesforce CPQ Configuration Rules Engine validates technical compatibility. Checks voltage compatibility (480V vs 230V), software version requirements, required accessories. Custom Apex handles complex edge cases. Flags engineering review for custom configurations. | K15: Feasibility assessment (Pass/Fail/Review); Compatibility warnings with specifics; Engineering escalation flags; Alternative valid configurations | L15: Configuration error rate reduction; Engineering escalation rate; First-time-right quotes %; Order cancellation reduction | N15: Low | O15: Limited direct revenue impact. Primarily operational efficiency. Consider bundling with related agents to increase value proposition. | P15: High | Q15: Quote and pricing processes are standardized across Siemens divisions. CPQ rules and approval workflows apply to DI, SI, and MO sales teams. | R15: Low | S15: Straightforward implementation. Primarily OOB configuration. Systems: Salesforce CPQ . Standard setup with minimal custom development. | T15: High | U15: Standard CRM data. ACP Level 2 sufficient for implementation. | V15: Low | W15: STATUS VALIDATED - NO COMPETING INITIATIVE: Technical feasibility. Checked: AF (12), DI (10), SI (9), SAP AI (16) - none address engineering validation. EXPANSION RISK: If Quoting Agent expands to product validation, coordinate. RECOMMENDATION: Proceed - fills current gap. | X15: Medium | Y15: Addresses [Inconsistent & Low-Quality Customer Interactions] pain point. 'Incompatible product configurations quoted to corporate accounts: 480V equipment for 230V facility, ...'. Moderate user impact. | Z15: Low | AA15: Limited direct revenue impact. Primarily operational efficiency. Consider bundling with related agents to increase value proposition. | AB15: Medium | AC15: Standard timeline: 3-6 months. 1 system integration. Key systems: Salesforce CPQ . Some custom development included.
A16: Quote Configuration Agent | B16: Upsell/Cross-sell Opportunity Sub-Agent | C16: Identifies additional products to propose based on the corporate account's installed base and current quote. Example: Account has 10 SIMATIC S7-1500 PLCs installed; suggest compatible I/O modules, programming software licenses, and service contracts they haven't purchased. | D16: [Missed Business Opportunities] Sales reps don't know corporate account's installed base. Miss upsell opportunities: account has 50 PLCs but hasn't been offered compatible HMI panels or service contracts. Estimated 15-20% revenue left on table per account. | E16: Qualifies - Salesforce Agentforce Sales | F16: RATIONALE: TECHNOLOGY: OOB: Salesforce Einstein Next Best Action + Agentforce Sales Agent | CUSTOM: MuleSoft for SAP data AI QUALIFICATION: YES - Einstein Next Best Action (NBA) uses ML to identify upsell patterns - Analyzes installed base, purchase history, product affinities - Agentforce Sales Agent surfaces AI-driven recommendations - Learns from sales success/failure patterns SIEMENS CRITERIA ASSESSMENT: - Business Value: HIGH (captures 15-20% revenue left on table) - Cross-business Applicability: HIGH (all divisions have installed base) - Technical Complexity: MEDIUM (OOB AI + MuleSoft integration) - ACP Compliance: Level 2 (OOB + MuleSoft integration) - Alignment with Initiatives: HIGH (cross-sell initiative, AI adoption) - User Impact: HIGH (proactive opportunity surfacing) PLATFORM FIT: Salesforce Agentforce Sales + Einstein NBA - AI-powered opportunity identification - MuleSoft provides SAP installed base data - Agentforce delivers recommendations conversationally CONCLUSION: Strong AI use case. Einstein NBA provides ML-based pattern recognition. MuleSoft integration is non-AI data plumbing. | G16: OOB: Salesforce Einstein Next Best Action | CONFIG: Define upsell rules based on installed base | AGENTFORCE: Sales Agent surfaces recommendations | CUSTOM: MuleSoft integration for SAP installed base data | H16: Einstein + Agentforce Sales Agent (OOB). MuleSoft for SAP data (CUSTOM). | I16: Current quote line items; Corporate account installed base (via MuleSoft from SAP); Product affinity rules; Service contract history | J16: Triggered during quote building. Salesforce Einstein Next Best Action identifies upsell/cross-sell opportunities based on installed base (e.g., account has S7-1500 PLCs → suggest compatible HMI panels). Agentforce Sales Agent surfaces recommendations proactively. Scores by likelihood and value. | K16: Ranked upsell opportunities with revenue potential; Cross-sell suggestions based on installed base; Success probability scores; Value messaging for sales rep | L16: Attach rate improvement; Average deal size increase %; Revenue captured vs. left on table; Installed base coverage | N16: High | O16: Strong business impact based on operational efficiency gains. Addresses [Missed Business Opportunities] pain point with measurable ROI. | P16: High | Q16: Quote and pricing processes are standardized across Siemens divisions. CPQ rules and approval workflows apply to DI, SI, and MO sales teams. | R16: Medium | S16: 2 system integrations required. Systems: MuleSoft, Agentforce Sales Agent. Some custom development needed. Standard connectors and APIs available. | T16: High | U16: Standard CRM data. ACP Level 2 sufficient for implementation. | V16: Low | W16: STATUS VALIDATED - UNIQUE TODAY: Upsell/cross-sell recommendations. Checked: AF (12) - SieSales Employee Agent summarizes, doesn't recommend. Checked: DI #1 (Account Planning) - summaries, not recommendations. EXPANSION RISK: Customer 360 could add 'next best action'. MONITOR roadmap. RECOMMENDATION: Proceed, architect for Customer 360 integration. | X16: High | Y16: Addresses critical pain: [Missed Business Opportunities]. Specific issue: 'Sales reps don't know corporate account's installed base...'. Quantified impact in source data. | Z16: High | AA16: Strong business impact based on operational efficiency gains. Addresses [Missed Business Opportunities] pain point with measurable ROI. | AB16: High | AC16: Extended timeline: >6 months. Complex factors: SAP integration, custom development. Plan for phased rollout.
A17: Quote Configuration Agent | B17: Quote Validation Sub-Agent | C17: Performs pre-submission checks on quotes: all required fields populated, pricing within policy limits, discount approvals obtained, product configurations valid, delivery dates feasible. Blocks submission if critical errors exist; warns on non-critical issues. | D17: [Manual, Time-Intensive Processes] Quote validation manual and inconsistent. Errors discovered at approval stage: missing PO reference, pricing outside policy, incomplete addresses. Each error cycles quote back, adding 2-5 days. Rework consumes sales capacity. | E17: Does not qualify as AI Agent | F17: RATIONALE: TECHNOLOGY: OOB: Salesforce CPQ Validation Rules + Flow Approval Routing AI QUALIFICATION: NO - Quote validation is deterministic rule checking: - Required fields present/missing = boolean check - Pricing within policy limits = numeric comparison - Discount approvals = threshold rules - Product configurations valid = constraint satisfaction - Approval routing follows configured matrix, not learned patterns - No ML model, no prediction, no learning from outcomes PREVIOUS OVERCLAIM CORRECTED: - "Agentforce Quoting Agent" was cited, but core functionality is CPQ rules - "AI-assisted validation beyond simple rule checking" was unsupported - Conversational interface for navigation ≠ AI decision-making SIEMENS CRITERIA ASSESSMENT: - Business Value: HIGH (error prevention) - Cross-business Applicability: HIGH (all quotes) - Technical Complexity: LOW (OOB CPQ) - ACP Compliance: Level 1 (OOB) - Alignment with Initiatives: HIGH - User Impact: HIGH CONCLUSION: This is workflow automation with validation rules, not an AI agent. The "intelligence" is configured business rules, not machine learning. | G17: OOB: Agentforce Quoting Agent, Salesforce CPQ Validation Rules | CONFIG: Define required fields, pricing policy limits, discount thresholds that trigger validation errors/warnings | H17: Agentforce Quoting Agent + CPQ (OOB). Configure validation rules. | I17: Complete quote data; CPQ validation rules; Approval policies; Required fields by quote type | J17: Triggered before quote submission. Agentforce Quoting Agent with Salesforce CPQ performs comprehensive validation: pricing within policy, discounts within limits, required fields populated (PO reference, ship-to), configurations valid. Determines approval routing. Blocks submission on critical errors; warns on non-critical. | K17: Validation results (Pass/Fail/Warning); Error list with specific fields; Approval routing decision; Risk flags | L17: Quote error rate reduction; Rework cycles eliminated; Time to validate; Approval rejection rate reduction | N17: Low | O17: Limited direct revenue impact. Primarily operational efficiency. Consider bundling with related agents to increase value proposition. | P17: High | Q17: Quote and pricing processes are standardized across Siemens divisions. CPQ rules and approval workflows apply to DI, SI, and MO sales teams. | R17: Medium | S17: 2 system integrations required. Systems: Agentforce Quoting Agent. Standard connectors and APIs available. | T17: High | U17: Standard CRM data. ACP Level 2 sufficient for implementation. | V17: Low | W17: FUTURE INITIATIVE ONLY: Quote validation relates to Quoting Agent. Checked: AF Row 8 (DISCUSSION), DI #4 (predefined) - not built yet. RECOMMENDATION: Proceed - capability valuable for future CPQ. | X17: High | Y17: Addresses critical pain: [Manual, Time-Intensive Processes]. Specific issue: 'Quote validation manual and inconsistent...'. Quantified impact in source data. | Z17: Low | AA17: Limited direct revenue impact. Primarily operational efficiency. Consider bundling with related agents to increase value proposition. | AB17: Low | AC17: Quick win: ≤3 months. Primarily OOB configuration. Systems: Agentforce Quoting Agent. Minimal dependencies.
A18: Quote Configuration Agent | B18: Configuration Rules Engine Sub-Agent | C18: Executes product configuration rules when sales reps build quotes. Enforces dependencies (Motor X requires Starter Y), exclusions (Product A incompatible with Product B), and quantity constraints (minimum order 10 units). Manages 10,000+ rules across product families. | D18: [Information Overload & Decision Paralysis] 10,000+ product configuration rules managed manually. Sales reps navigate complex BOM dependencies without guidance. Configuration errors on 15% of complex quotes. Decision paralysis when faced with interdependent product choices. | E18: Does not qualify as AI Agent | F18: RATIONALE: TECHNOLOGY: OOB: Salesforce CPQ Advanced Product Rules + Custom Apex AI QUALIFICATION: NO - 10,000+ rules are explicit constraints, not learned patterns - Dependencies (Motor X requires Starter Y) are engineering facts - Exclusions and quantity constraints are deterministic - Rule execution is algorithmic constraint satisfaction - Even "complex" Apex is still deterministic logic SIEMENS CRITERIA ASSESSMENT: - Business Value: HIGH (prevents 15% configuration error rate) - Cross-business Applicability: HIGH (all product divisions) - Technical Complexity: HIGH (10,000+ rules, complex constraints) - ACP Compliance: Level 2 (OOB CPQ + custom Apex) - Alignment with Initiatives: HIGH (product configuration accuracy) - User Impact: HIGH (guided configuration reduces errors) CONCLUSION: High complexity but NOT AI. Rule quantity doesn't create AI need. CPQ Advanced handles complex constraint logic. Custom Apex for edge cases is still deterministic. Valuable functionality but correctly labeled as "Rules Engine" not "Agent". | G18: OOB: Salesforce CPQ Advanced Product Rules (supports 10,000+ rules) | CONFIG: Define dependencies, exclusions, quantity constraints per product family | CUSTOM: Apex for complex constraint logic | H18: Salesforce CPQ Advanced (OOB). CUSTOM Apex for complex constraints. | I18: Product catalog (10,000+ SKUs); Configuration rules repository (dependencies, exclusions, quantities); Product compatibility matrices; Historical valid configurations | J18: Triggered when products added to quote. Salesforce CPQ Advanced loads applicable rules by product family. Executes constraint-based logic: validates compatibility, enforces dependencies (Motor X requires Starter Y), calculates BOM. Custom Apex handles complex industrial equipment constraints. Caches frequent rule sets for performance. | K18: Validated product configuration; Assembled BOM with quantities; Conflict resolution suggestions; Configuration completeness score; Rule execution trace | L18: Configuration error rate reduction; Quote generation time for complex deals; First-time-right rate; Engineering rework hours saved | N18: Low | O18: Limited direct revenue impact. Primarily operational efficiency. Consider bundling with related agents to increase value proposition. | P18: High | Q18: Quote and pricing processes are standardized across Siemens divisions. CPQ rules and approval workflows apply to DI, SI, and MO sales teams. | R18: Low | S18: Straightforward implementation. Primarily OOB configuration. Systems: Salesforce CPQ . Standard setup with minimal custom development. | T18: High | U18: Standard CRM data. ACP Level 2 sufficient for implementation. | V18: Low | W18: FUTURE INITIATIVE ONLY: Configuration rules relate to Quoting Agent. Checked: AF Row 8 (DISCUSSION), DI #4 (predefined) - not built yet. RECOMMENDATION: Proceed. Design rules to be portable to future CPQ. | X18: High | Y18: Addresses critical pain: [Information Overload & Decision Paralysis]. Specific issue: '10,000+ product configuration rules managed manually...'. Quantified impact in source data. | Z18: Low | AA18: Limited direct revenue impact. Primarily operational efficiency. Consider bundling with related agents to increase value proposition. | AB18: Medium | AC18: Standard timeline: 3-6 months. 1 system integration. Key systems: Salesforce CPQ . Some custom development included.
A19: Credit Decision Agent | B19: Credit Data Aggregation Sub-Agent | C19: Retrieves commercial credit data for corporate accounts from: D&B credit reports, Experian business credit, internal AR aging (how this account pays Siemens), and trade references (how they pay other suppliers). Consolidates into single credit package. | D19: [Manual, Time-Intensive Processes] Credit analyst manually gathers data from 5+ sources: D&B portal, Experian, internal AR, trade references. 3-4 hours per corporate account. No automation. Credit decisions delayed 2-3 days while analyst hunts for information. | E19: Does not qualify as AI Agent | F19: RATIONALE: TECHNOLOGY: CUSTOM: MuleSoft orchestration + custom aggregation logic AI QUALIFICATION: NO - Multi-source API orchestration is integration work - Parallel API calls to D&B, Experian, SAP AR are deterministic - Data consolidation follows fixed transformation rules - Error handling is programmatic, not intelligent - No learning, prediction, or NLP involved SIEMENS CRITERIA ASSESSMENT: - Business Value: HIGH (saves 3-4 hours per credit check) - Cross-business Applicability: HIGH (all divisions need credit data) - Technical Complexity: MEDIUM (multi-API orchestration) - ACP Compliance: Level 2 (custom MuleSoft integration) - Alignment with Initiatives: HIGH (integration platform) - User Impact: HIGH (2-3 day delay eliminated) CONCLUSION: Valuable integration but NOT an AI agent. MuleSoft orchestration calling multiple APIs is standard ETL/integration work. Rename to "Credit Data Aggregation Service" or similar. | G19: CUSTOM: Multi-source credit aggregation agent. No OOB product consolidates D&B + Experian + SAP AR + trade references. Build with MuleSoft orchestration + custom aggregation logic. | H19: CUSTOM. MuleSoft + custom aggregation logic. | I19: D&B API; Experian API; SAP S/4HANA FI-AR (internal AR aging, payment history); Trade reference database; Corporate hierarchy data | J19: Triggered on credit check request. Custom MuleSoft orchestration calls multiple sources in parallel: D&B credit report, Experian business credit, SAP AR aging (how this account pays Siemens), trade references. Consolidates into single credit package. Handles API timeouts/errors gracefully. | K19: Consolidated credit package; Bureau scores (D&B, Experian); Internal payment history summary; Trade reference results; Data completeness indicator | L19: Data retrieval time (target: <30 seconds vs. 3-4 hours manual); API success rate; Data completeness score; Credit analyst time saved | N19: Low | O19: Limited direct revenue impact. Primarily operational efficiency. Consider bundling with related agents to increase value proposition. | P19: Medium | Q19: Primarily serves specific use case but adaptable. Credit assessment applies to all B2B customers regardless of division. Risk scoring and payment terms are enterprise-wide policies. | R19: Medium | S19: 2 system integrations required. Systems: MuleSoft. Some custom development needed. Standard connectors and APIs available. | T19: Low | U19: ⚠️ POTENTIAL BLOCKER: Accesses external credit bureau APIs (D&B, Experian) and SAP FI-AR payment history. This is ACTUAL financial data requiring ACP Level 3 review. Verify data classification with Siemens Data Governance. | V19: Low | W19: STATUS VALIDATED - NO COMPETING INITIATIVE: Credit data aggregation. Checked: AF Tab (12 initiatives) - none address credit. Checked: DI Use Cases (10) - none address credit/finance (#1-10 are sales/service focused). Checked: SAP AI (16) - A1 processes AR, doesn't aggregate for credit decisions. Checked: SI Projects (9) - none address credit. RECOMMENDATION: Proceed - unique finance capability. | X19: High | Y19: Addresses critical pain: [Manual, Time-Intensive Processes]. Specific issue: 'Credit analyst manually gathers data from 5+ sources: D&B portal, Experian, internal AR, trade references...'. Quantified impact in source data. | Z19: Low | AA19: Limited direct revenue impact. Primarily operational efficiency. Consider bundling with related agents to increase value proposition. | AB19: High | AC19: Extended timeline: >6 months. Complex factors: custom development. Plan for phased rollout.
A20: Credit Decision Agent | B20: Risk Scoring Sub-Agent | C20: Calculates a credit risk score (0-1000) for corporate accounts using: external credit bureau scores, financial statement ratios (current ratio, debt/equity), payment history with Siemens (DSO, late payment frequency), and industry risk factors. Higher score = lower risk. | D20: [Inconsistent & Low-Quality Customer Interactions] Credit risk assessment varies by region and analyst. Same corporate account rated 'low risk' in Germany, 'medium risk' in USA. No standardized model. Inconsistent decisions damage customer relationships and revenue. | E20: Qualifies - Custom AI Agent | F20: RATIONALE: TECHNOLOGY: CUSTOM: ML credit scoring model (Salesforce Einstein ML or SAP Analytics Cloud) AI QUALIFICATION: YES - Custom AI Agent (ACP Level 3) ML MODEL SPECIFICATION: - Model Type: Gradient Boosted Decision Trees (XGBoost/LightGBM) or Neural Network - Training Data: 5+ years of Siemens AR transaction history, 10,000+ corporate accounts - Key Features: * External credit bureau scores (D&B, Experian) * Financial ratios (current ratio, debt/equity, interest coverage) * Payment history metrics (DSO, late payment frequency, dispute rate) * Industry risk factors (sector volatility, economic indicators) * Corporate hierarchy exposure (parent/subsidiary aggregation) - Target Variable: Probability of default within 12 months - Validation Metrics: AUC-ROC >0.80, Precision >0.75 at 20% recall - Model Refresh: Monthly retraining with rolling 5-year window - Inference: Real-time scoring via API (<100ms latency) WHY ML IS REQUIRED: - D&B/Experian scores don't reflect Siemens-specific payment behavior - Complex non-linear interactions between features (industry + size + payment history) - Need to predict future default, not just describe current state - Siemens-specific risk factors not captured in generic bureau models SIEMENS CRITERIA ASSESSMENT: - Business Value: HIGH (reduced bad debt, consistent risk assessment) - Cross-business Applicability: HIGH (all B2B credit decisions) - Technical Complexity: HIGH (custom ML pipeline) - ACP Compliance: Level 3 (Custom AI) - Alignment with Initiatives: HIGH (AI-first strategy) - User Impact: HIGH (credit analysts, sales) CONCLUSION: Qualifies as Custom AI Agent - ML model trained on Siemens-specific data to predict default probability, going beyond deterministic rule-based scoring. | G20: CUSTOM: ML credit scoring model - Platform: Salesforce Einstein ML or SAP Analytics Cloud - Algorithm: XGBoost/LightGBM ensemble or Neural Network - Training: Siemens AR history (5+ years, 10K+ accounts) - Features: Bureau scores, financial ratios, payment patterns, industry risk - Inference: Real-time API (<100ms) - Refresh: Monthly retraining | INTEGRATION: MuleSoft for feature aggregation from D&B, Experian, SAP FI-AR | H20: CUSTOM. Train ML model on Siemens AR data. | I20: Aggregated credit data from Sub-Agent 16; SAP AR historical defaults; Financial statement ratios; Industry risk factors; Corporate hierarchy exposure | J20: Triggered after data aggregation. Custom ML model (Salesforce Einstein ML or SAP Analytics Cloud) calculates risk score. Trained on Siemens-specific default history. Inputs: bureau scores, payment patterns, financial ratios (current ratio, debt/equity), industry risk. Outputs probability of default. | K20: Risk score (0-1000, higher = lower risk); Risk category (A-E); Default probability %; Contributing risk factors ranked; Confidence level | L20: Model accuracy vs. actual defaults (AUC >0.8 target); Score stability over time; Bad debt reduction %; Credit decision consistency across regions | N20: Low | O20: Limited direct revenue impact. Primarily operational efficiency. Consider bundling with related agents to increase value proposition. | P20: Medium | Q20: Primarily serves specific use case but adaptable. Credit assessment applies to all B2B customers regardless of division. Risk scoring and payment terms are enterprise-wide policies. | R20: High | S20: Complex implementation: 1 systems (multiple platforms). Custom ML model development and training required. Estimated significant technical effort. | T20: Low | U20: ⚠️ POTENTIAL BLOCKER: May require ACP Level 3 due to sensitive data access. | V20: Low | W20: STATUS VALIDATED - NO COMPETING INITIATIVE: Risk scoring for credit. Checked: AF (12), DI (10), SI (9), SAP AI (16) - none address credit risk scoring. RECOMMENDATION: Proceed - unique capability. | X20: Low | Y20: Pain point documented but limited scope: [Inconsistent & Low-Quality Customer Interactions]. May affect smaller user population. | Z20: Low | AA20: Limited direct revenue impact. Primarily operational efficiency. Consider bundling with related agents to increase value proposition. | AB20: High | AC20: Extended timeline: >6 months. Complex factors: custom development, ML model training. Plan for phased rollout.
A21: Credit Decision Agent | B21: Credit Limit Calculation Sub-Agent | C21: Determines how much credit to extend to a corporate account based on: risk score, requested order value, existing outstanding receivables, customer's annual revenue, and Siemens exposure policy (e.g., max 5% of customer's annual revenue). | D21: [Inconsistent & Low-Quality Customer Interactions] Credit limits set arbitrarily without risk-based methodology. Over-exposure to high-risk accounts causes bad debt. Under-serving low-risk strategic accounts loses business to competitors. Inconsistent treatment across similar accounts. | E21: Does not qualify as AI Agent | F21: RATIONALE: TECHNOLOGY: OOB: SAP Credit Management (S/4HANA module) AI QUALIFICATION: NO - Limit calculation uses configured formulas - Risk score × revenue × exposure policy = deterministic math - No learning or prediction - just formula application - SAP Credit Management is rule-based calculation engine SIEMENS CRITERIA ASSESSMENT: - Business Value: HIGH (risk-based limits vs. arbitrary) - Cross-business Applicability: HIGH (all credit decisions) - Technical Complexity: LOW (OOB with configuration) - ACP Compliance: Level 1 (OOB SAP module) - Alignment with Initiatives: HIGH (S/4HANA deployment) - User Impact: HIGH (consistent limit methodology) CONCLUSION: OOB SAP Credit Management functionality. Formula-based calculation is NOT AI. Valuable but correctly labeled as "Calculation" not "Agent". | G21: OOB: SAP Credit Management (S/4HANA module) - automatic limit calculation, exposure monitoring | CONFIG: Define limit formulas based on risk score, customer revenue, Siemens exposure policy | H21: SAP Credit Management (OOB). Configure limit formulas. | I21: Risk score from Sub-Agent 17; Corporate account financial data; Order value requested; Existing exposure; Siemens exposure policy rules | J21: Triggered after risk scoring. SAP Credit Management calculates recommended limit using configured formulas. Considers: risk score, customer annual revenue (max 5% exposure rule), existing outstanding receivables, requested order value. Optimizes for risk-adjusted return. | K21: Recommended credit limit (€); Limit justification; Required collateral/guarantees if high-risk; Monitoring thresholds; Comparison to requested amount | L21: Limit utilization rate; Credit losses as % of exposure; Revenue enabled by appropriate limits; Over/under-exposure incidents | N21: High | O21: Strong business impact based on operational efficiency gains. Addresses [Inconsistent & Low-Quality Customer Interactions] pain point with measurable ROI. | P21: Medium | Q21: Primarily serves specific use case but adaptable. Credit assessment applies to all B2B customers regardless of division. Risk scoring and payment terms are enterprise-wide policies. | R21: Medium | S21: 1 system integration required. Systems: SAP C. Standard connectors and APIs available. | T21: Low | U21: ⚠️ POTENTIAL BLOCKER: May require ACP Level 3 due to sensitive data access. | V21: Low | W21: STATUS VALIDATED - NO COMPETING INITIATIVE: Credit limit calculation. Checked: AF (12), DI (10), SI (9), SAP AI (16) - none address credit limits. RECOMMENDATION: Proceed - unique finance capability. | X21: Low | Y21: Pain point documented but limited scope: [Inconsistent & Low-Quality Customer Interactions]. May affect smaller user population. | Z21: High | AA21: Strong business impact based on operational efficiency gains. Addresses [Inconsistent & Low-Quality Customer Interactions] pain point with measurable ROI. | AB21: Medium | AC21: Standard timeline: 3-6 months. 1 system integration. Key systems: SAP C.
A22: Credit Decision Agent | B22: Approval Routing Sub-Agent | C22: ⚠️ DUPLICATE OF Row 32 (Approver Selection) - Both use SF Flow approval routing. RECOMMEND MERGE. | Routes credit decisions to the correct approver based on amount and risk: <€50K auto-approved if score >700; €50K-€500K requires regional credit manager; >€500K requires corporate credit committee. Handles delegation when approvers are unavailable. | D22: [Manual, Time-Intensive Processes] Credit approvals stuck in manual queues. Approver on vacation - no delegation. Urgent €1M deal waits 5-10 days. No escalation automation. Manual tracking via email. Sales velocity killed by process bottlenecks. | E22: Does not qualify as AI Agent | F22: RATIONALE: TECHNOLOGY: OOB: Salesforce Flow approval routing + org hierarchy lookup AI QUALIFICATION: NO - Routing logic is deterministic matrix: - <€50K + score >700 = auto-approve - €50K-€500K = regional credit manager - >€500K = credit committee - Delegation rules are configured policies, not learned - Approver availability is calendar lookup - SLA tracking is timer-based PREVIOUS OVERCLAIM CORRECTED: - "YES (PARTIAL)" was invalid - partial AI is not a category - "Agentforce Employee Agent provides AI-assisted guidance" was vague - If core routing is deterministic, adding chat doesn't make it AI SIEMENS CRITERIA ASSESSMENT: - Business Value: HIGH (faster approvals) - Cross-business Applicability: HIGH (all credit decisions) - Technical Complexity: LOW (OOB Flow) - ACP Compliance: Level 1 (OOB) - Alignment with Initiatives: HIGH - User Impact: HIGH CONCLUSION: This is workflow automation with configurable routing rules. The approver matrix is business logic, not machine learning. | G22: OOB: Salesforce Flow approval routing | CONFIG: Define routing matrix by amount/risk/region, delegation rules, escalation paths | AGENTFORCE: Employee Agent assists credit analysts | H22: Salesforce Flow + Agentforce Employee Agent (OOB). Configure routing matrix. | I22: Risk assessment results; Credit limit recommendation; Approval policy matrix (amount × risk); Approver hierarchy; Approver availability | J22: Triggered after limit calculation. Salesforce Flow routes based on policy: <€50K auto-approved if score >700; €50K-€500K to regional credit manager; >€500K to credit committee. Agentforce Employee Agent assists credit analysts with context. Handles delegation when approvers unavailable. Sets SLAs. | K22: Approval workflow route; Required approvers with sequence; Justification package for approvers; SLA timers; Delegation assignments | L22: Auto-approval rate for low-risk; Approval cycle time (target: <24h for standard); Escalation rate; Deals lost due to credit delays | M22: Slack Agent routes notifications and approval requests directly to Slack channels for quick action. | N22: Low | O22: Limited direct revenue impact. Primarily operational efficiency. Consider bundling with related agents to increase value proposition. | P22: Medium | Q22: Primarily serves specific use case but adaptable. Credit assessment applies to all B2B customers regardless of division. Risk scoring and payment terms are enterprise-wide policies. | R22: Medium | S22: 2 system integrations required. Systems: Agentforce Employee Agent. Standard connectors and APIs available. | T22: Medium | U22: NEEDS REVIEW: Accesses credit limit recommendations and approval policy matrix. Uses financial context but may not access raw credit data. Verify if credit limit values require ACP Level 3. | V22: Low | W22: STATUS VALIDATED - NO COMPETING INITIATIVE: Credit approval routing. Checked: AF (12), DI (10), SI (9), SAP AI (16) - none address credit approval workflows. RECOMMENDATION: Proceed - unique workflow capability. | X22: High | Y22: Addresses critical pain: [Manual, Time-Intensive Processes]. Specific issue: 'Credit approvals stuck in manual queues...'. Quantified impact in source data. | Z22: Low | AA22: Limited direct revenue impact. Primarily operational efficiency. Consider bundling with related agents to increase value proposition. | AB22: Low | AC22: Quick win: ≤3 months. Primarily OOB configuration. Systems: Agentforce Employee Agent. Minimal dependencies.
A23: Credit Decision Agent | B23: Credit Monitoring Sub-Agent | C23: Continuously monitors approved corporate accounts for credit deterioration: payment delays increasing, credit bureau score drops, news of financial distress, significant order pattern changes. Triggers alerts to credit team when thresholds breached. | D23: [Missed Business Opportunities] Credit deterioration discovered after losses occur. Corporate account bankruptcy - no early warning. Payment patterns worsened over 6 months - nobody noticed. Reactive write-offs instead of proactive intervention. Revenue leakage. | E23: Qualifies - Custom AI Agent | F23: RATIONALE: TECHNOLOGY: OOB: SAP Credit Management monitoring + CUSTOM: ML early warning model AI QUALIFICATION: YES - Custom AI Agent (ACP Level 3) ML MODEL SPECIFICATION: - Model Type: LSTM (Long Short-Term Memory) for time-series pattern detection - Training Data: Historical deterioration → default sequences (3+ years) - Key Features (time-series): * Payment timeliness trend (DSO rolling 30/60/90 days) * Credit utilization trajectory * Order pattern changes (volume, frequency, product mix) * Bureau score changes (delta over time) * Support ticket sentiment trends - Target: Early warning signal 30-60 days before threshold breach - Validation: Detection rate >70% with <15% false positive rate - Threshold: Alert when predicted risk score increases >20% in 30 days - Inference: Batch scoring daily, real-time on significant events WHY ML IS REQUIRED: - SAP OOB monitoring is reactive (alerts AFTER threshold breach) - ML model detects PATTERNS of deterioration before explicit triggers - Learns from historical sequences: payment delays → disputes → defaults - Captures non-linear combinations that humans miss SIEMENS CRITERIA ASSESSMENT: - Business Value: HIGH (early intervention reduces bad debt) - Cross-business Applicability: HIGH (all credit accounts) - Technical Complexity: HIGH (time-series ML) - ACP Compliance: Level 3 (Custom AI) - Alignment with Initiatives: HIGH (predictive analytics) - User Impact: HIGH (credit risk team) CONCLUSION: Qualifies as Custom AI Agent - LSTM model detects deterioration patterns 30-60 days before traditional threshold-based alerts. | G23: OOB: SAP Credit Management monitoring (threshold alerts, utilization tracking) | CUSTOM: ML early warning model - Platform: SAP Analytics Cloud or Salesforce Einstein - Algorithm: LSTM (time-series) + Gradient Boosting ensemble - Training: Historical deterioration sequences (3+ years) - Features: Payment trends, utilization trajectory, bureau deltas - Inference: Daily batch + real-time event triggers - Lead Time: 30-60 days early warning | INTEGRATION: SAP Credit Management API for threshold configuration | H23: SAP Credit Management (OOB). CUSTOM ML for predictive alerts. | I23: Approved credit limits; SAP AR transaction activity; Payment performance trends; Credit bureau alert feeds; Order pattern changes | J23: Continuously monitors via SAP Credit Management. Tracks: credit utilization, payment timeliness (DSO trend), bureau score changes. Custom ML model detects early warning patterns (payment delays increasing, order pattern changes). Triggers alerts for deteriorating accounts. Recommends limit adjustments or holds. | K23: Monitoring alerts with severity; Limit adjustment recommendations; Payment hold triggers; Early warning notifications; Portfolio risk dashboard | L23: Early warning accuracy (detect issues 30+ days before default); Limit breach incidents prevented; Bad debt reduction from proactive action | N23: Low | O23: Limited direct revenue impact. Primarily operational efficiency. Consider bundling with related agents to increase value proposition. | P23: Medium | Q23: Primarily serves specific use case but adaptable. Credit assessment applies to all B2B customers regardless of division. Risk scoring and payment terms are enterprise-wide policies. | R23: High | S23: Complex implementation: 1 systems (SAP C). SAP integration requires middleware and data mapping. Custom ML model development and training required. Estimated significant technical effort. | T23: Low | U23: ⚠️ POTENTIAL BLOCKER: Accesses SAP AR transaction activity, payment performance trends, and credit bureau alert feeds. Contains actual payment behavior data requiring ACP Level 3. Verify with Data Governance. | V23: Low | W23: STATUS VALIDATED - NO COMPETING INITIATIVE: Credit monitoring. Checked: AF (12), DI (10), SI (9), SAP AI (16) - none address ongoing credit monitoring. RECOMMENDATION: Proceed - unique monitoring capability. | X23: Medium | Y23: Addresses [Missed Business Opportunities] pain point. 'Credit deterioration discovered after losses occur...'. Moderate user impact. | Z23: Low | AA23: Limited direct revenue impact. Primarily operational efficiency. Consider bundling with related agents to increase value proposition. | AB23: High | AC23: Extended timeline: >6 months. Complex factors: SAP integration, custom development, ML model training. Plan for phased rollout.
A24: Credit Decision Agent | B24: Payment History Analysis Sub-Agent [NEW] | C24: Analyzes how a corporate account actually pays Siemens invoices: average days to pay (DSO), frequency of late payments, dispute rates, partial payment patterns. Combines with external credit data for complete risk picture. Example: D&B says 'low risk' but account pays Siemens 45 days late on average. | D24: [Data Fragmentation & Siloed Information] Internal payment history (how corporate account pays Siemens) siloed in AR system. External credit scores don't reflect Siemens-specific behavior. Account pays D&B-rated suppliers on time but pays Siemens 45+ days late - invisible. | E24: Qualifies - Custom AI Agent | F24: RATIONALE: TECHNOLOGY: CUSTOM: ML model on SAP FI-AR payment history AI QUALIFICATION: YES - Custom AI Agent (ACP Level 3) ML MODEL SPECIFICATION: - Model Type: Gradient Boosted Trees + Clustering (K-Means for behavior segmentation) - Training Data: SAP FI-AR transaction history (3+ years, 100K+ invoices) - Key Features: * Days Sales Outstanding (DSO) - mean, std, trend * Late payment frequency and severity (days late distribution) * Partial payment patterns (% paid on time, % paid late, % disputed) * Dispute rate and resolution time * Seasonality patterns (month-end, quarter-end behavior) * Payment method preferences (wire, check, ACH timing) - Target: Payment behavior score (0-100) + behavior classification - Behavior Classes: Prompt (pays <5 days), Standard (5-30 days), Slow (30-60 days), Erratic (high variance) - Trend Detection: Improving (+5% DSO improvement/quarter), Stable, Deteriorating - Validation: Classification accuracy >85%, DSO prediction MAE <5 days WHY ML IS REQUIRED: - External credit scores don't reflect how customer pays SIEMENS specifically - Pattern classification requires unsupervised learning (clustering) - Trend detection from noisy AR data needs ML smoothing - Combines multiple signals into single actionable score SIEMENS CRITERIA ASSESSMENT: - Business Value: HIGH (Siemens-specific credit insight) - Cross-business Applicability: HIGH (all AR accounts) - Technical Complexity: HIGH (custom ML on AR data) - ACP Compliance: Level 3 (Custom AI) - Alignment with Initiatives: HIGH (data-driven credit) - User Impact: HIGH (credit analysts) CONCLUSION: Qualifies as Custom AI Agent - ML model provides Siemens-specific payment behavior scoring that external bureaus cannot offer. | G24: CUSTOM: ML payment behavior analysis - Platform: SAP Analytics Cloud or Python ML pipeline - Algorithm: XGBoost for scoring + K-Means for behavior clustering - Training: SAP FI-AR history (3+ years, 100K+ invoices) - Features: DSO statistics, late payment distribution, dispute rates, seasonality - Output: Behavior score (0-100), classification (Prompt/Standard/Slow/Erratic), trend - Inference: Real-time on demand, batch refresh weekly | DATA SOURCE: SAP S/4HANA FI-AR via MuleSoft extraction | H24: CUSTOM. ML model on SAP AR payment history. | I24: SAP S/4HANA FI-AR: AR aging reports, payment transactions, invoice history, dispute records, credit memos; Bank remittance data; Customer payment terms | J24: Triggered during credit assessment. Custom ML model queries SAP AR for payment history: average DSO, late payment frequency, partial payment patterns, dispute rates. Calculates internal payment behavior score (0-100). Identifies trends (improving/deteriorating). Score combined with external data for holistic risk view. | K24: Payment behavior score (0-100); Average DSO and trend direction; Late payment frequency and severity; Dispute rate; Pattern classification (prompt/slow/erratic); Trend alerts | L24: Prediction accuracy for payment delays; Bad debt reduction; DSO improvement for monitored accounts; Credit decision accuracy lift vs. external-only data | N24: Low | O24: Limited direct revenue impact. Primarily operational efficiency. Consider bundling with related agents to increase value proposition. | P24: Medium | Q24: Primarily serves specific use case but adaptable. Credit assessment applies to all B2B customers regardless of division. Risk scoring and payment terms are enterprise-wide policies. | R24: High | S24: Complex implementation: 1 systems (SAP AR). SAP integration requires middleware and data mapping. Custom ML model development and training required. Estimated significant technical effort. | T24: Low | U24: ⚠️ POTENTIAL BLOCKER: Directly accesses SAP S/4HANA FI-AR: AR aging reports, payment transactions, invoice history, dispute records. This is core financial data requiring ACP Level 3. Verify with Data Governance. | V24: Medium | W24: RELATED SAP SOLUTION: SAP Accounts Receivable Agent (A1) - AVAILABLE in SAP Joule catalog, NOT DEPLOYED at Siemens. (SOURCE: SAP Joule Feature List - external). SAP A1 function: Automates AR processing - invoicing, collections, payment matching within S/4HANA. SPECIFIC DIFFERENTIATOR: Payment History Analysis provides SALESFORCE-visible payment insights for sales reps (customer payment patterns, credit risk signals). A1 is finance-back-office focused. Checked: AF (12), DI (10), SI (9) - NONE provide CRM-integrated payment visibility. | X24: Medium | Y24: Addresses [Data Fragmentation & Siloed Information] pain point. 'Internal payment history (how corporate account pays Siemens) siloed in AR system...'. Moderate user impact. | Z24: Low | AA24: Limited direct revenue impact. Primarily operational efficiency. Consider bundling with related agents to increase value proposition. | AB24: High | AC24: Extended timeline: >6 months. Complex factors: SAP integration, custom development, ML model training. Plan for phased rollout.
A25: Compliance Orchestration Agent | B25: Sanctions Screening Sub-Agent | C25: Screens corporate account names, addresses, and beneficial owners against sanctions lists (OFAC SDN, EU Consolidated, UN Security Council) before quote approval. Uses name matching algorithms to catch variations (e.g., 'Al-Qaeda' vs 'Al Qaeda' vs 'القاعدة'). | D25: [Manual, Time-Intensive Processes] Manual sanctions screening: 30-60 minutes per corporate account. Compliance team processes 50+ daily. Copy-paste names into OFAC search. Human error risk on name variations. Team burnout from repetitive, time-intensive checking. | E25: Does not qualify as AI Agent | F25: RATIONALE: TECHNOLOGY: OOB: SAP GTS Sanctioned Party List Screening AI QUALIFICATION: NO - Fuzzy name matching uses deterministic algorithms (Levenshtein distance, Soundex, phonetic matching) - Alias detection is database lookup, not learned patterns - List updates are regulatory feeds, not AI learning - Match sensitivity is configured threshold, not adaptive SIEMENS CRITERIA ASSESSMENT: - Business Value: HIGH (saves 30-60 min per account, critical compliance) - Cross-business Applicability: HIGH (all international transactions) - Technical Complexity: LOW (OOB SAP GTS) - ACP Compliance: Level 1 (OOB platform) - Alignment with Initiatives: HIGH (compliance automation) - User Impact: HIGH (reduces team burnout from repetitive checks) CONCLUSION: Critical compliance function but SAP GTS is rules and matching algorithms, not AI. "Fuzzy matching" is algorithmic string similarity, not machine learning. | G25: OOB: SAP GTS Sanctioned Party List Screening - auto-updating OFAC/EU/UN lists, fuzzy name matching, alias detection | CONFIG: Set matching sensitivity thresholds | H25: SAP GTS (OOB). Configure matching sensitivity. | I25: Corporate account name and aliases; Registered addresses; Beneficial owners; OFAC SDN list; EU Consolidated list; UN Security Council list (auto-updated in SAP GTS) | J25: Triggered on corporate account creation and quote validation. SAP GTS Sanctioned Party List Screening checks against all major lists. Fuzzy name matching catches variations (Al-Qaeda vs Al Qaeda). Configurable match sensitivity. Screens beneficial owners for shell company risk. | K25: Screening result (Clear/Hit/Review); Match details with confidence score; Matched list and entry; Recommended action; Audit documentation | L25: Screening time (<5 seconds target); False positive rate (<2% target); Compliance team time saved (30-60 min per manual screen); Sanction violation prevention | N25: Low | O25: Limited direct revenue impact. Primarily operational efficiency. Consider bundling with related agents to increase value proposition. | P25: Medium | Q25: Primarily serves specific use case but adaptable. Applicable across divisions with customization. Core functionality in "Compliance Orchestration Agent" serves common business processes. | R25: Medium | S25: 1 system integration required. Systems: SAP GTS. Standard connectors and APIs available. | T25: High | U25: Standard CRM data. ACP Level 2 sufficient for implementation. | V25: Low | W25: STATUS VALIDATED - NO COMPETING INITIATIVE: Sanctions screening. Checked: AF (12), DI (10), SI (9), SAP AI (16) - NONE address trade compliance/sanctions. DI Use Cases are sales/service focused (#1-10), not compliance. RECOMMENDATION: Proceed - critical compliance gap. | X25: High | Y25: Addresses critical pain: [Manual, Time-Intensive Processes]. Specific issue: 'Manual sanctions screening: 30-60 minutes per corporate account...'. Quantified impact in source data. | Z25: Low | AA25: Limited direct revenue impact. Primarily operational efficiency. Consider bundling with related agents to increase value proposition. | AB25: Medium | AC25: Standard timeline: 3-6 months. 1 system integration. Key systems: SAP GTS.
A26: Compliance Orchestration Agent | B26: Export Control Classification Sub-Agent | C26: Determines export classification codes (ECCN/EAR99) for products being quoted and checks if export license is required based on: product classification, destination country, end-user, and end-use. Example: SIMATIC controllers to Iran require BIS license. | D26: [Manual, Time-Intensive Processes] Export classification (ECCN) determined manually. Sales rep asks product management. 1-2 day turnaround. No systematic classification database. Quotes to controlled destinations delayed. Manual process doesn't scale. | E26: Does not qualify as AI Agent | F26: RATIONALE: TECHNOLOGY: OOB: SAP GTS Export Control Classification AI QUALIFICATION: NO - ECCN determination is database lookup against product master - License requirements are rule-based (product + destination + end-user matrix) - Classification follows regulatory definitions, not learned patterns - No prediction or NLP involved SIEMENS CRITERIA ASSESSMENT: - Business Value: HIGH (eliminates 1-2 day classification delays) - Cross-business Applicability: HIGH (all export transactions) - Technical Complexity: LOW (OOB with configuration) - ACP Compliance: Level 1 (OOB SAP GTS) - Alignment with Initiatives: HIGH (export compliance automation) - User Impact: HIGH (scales classification systematically) CONCLUSION: Essential export compliance but purely database-driven. ECCN master data + regulatory rules = deterministic classification. | G26: OOB: SAP GTS Export Control Classification - ECCN/EAR99 determination, license requirements, destination screening | CONFIG: Load Siemens product ECCN master data | H26: SAP GTS (OOB). Configure product classifications. | I26: Product details and technical specs; Siemens ECCN master data; Export control databases (CCL, EAR); Destination country; End-user type | J26: Triggered when products added to quote. SAP GTS Export Control Classification determines ECCN/EAR99. Checks license requirements based on product classification + destination + end-user. Flags controlled items requiring license. Auto-classifies known products from Siemens ECCN master. | K26: Product classification code (ECCN or EAR99); License requirement (Yes/No/Conditional); Destination restrictions; Required documentation; Classification confidence | L26: Classification accuracy (>99% target); Licensing compliance rate; Classification time vs. manual (1-2 days); Export violation prevention | N26: High | O26: Strong business impact with quantified targets: >99%, 2 days. Addresses [Manual, Time-Intensive Processes] pain point with measurable ROI. | P26: Medium | Q26: Primarily serves specific use case but adaptable. Applicable across divisions with customization. Core functionality in "Compliance Orchestration Agent" serves common business processes. | R26: Medium | S26: 1 system integration required. Systems: SAP GTS. Standard connectors and APIs available. | T26: High | U26: Standard CRM data. ACP Level 2 sufficient for implementation. | V26: Low | W26: STATUS VALIDATED - NO COMPETING INITIATIVE: Export control classification. Checked: AF (12), DI (10), SI (9), SAP AI (16) - none address export compliance. RECOMMENDATION: Proceed - unique compliance capability. | X26: Medium | Y26: Addresses [Manual, Time-Intensive Processes] pain point. 'Export classification (ECCN) determined manually...'. Moderate user impact. | Z26: High | AA26: Strong business impact with quantified targets: >99%, 2 days. Addresses [Manual, Time-Intensive Processes] pain point with measurable ROI. | AB26: Medium | AC26: Standard timeline: 3-6 months. 1 system integration. Key systems: SAP GTS.
A27: Compliance Orchestration Agent | B27: Denied Party Screening Sub-Agent | C27: Screens all parties in the transaction (buyer, ship-to, end-user, freight forwarder, intermediaries) against denied party lists (BIS Entity List, State Department debarred). Checks corporate ownership to detect shell companies hiding restricted entities. | D27: [Manual, Time-Intensive Processes] Denied party lists update weekly with 500+ changes. Manual screening cannot keep pace. Compliance team maintains spreadsheets. No automated monitoring. Time-intensive process creates bottleneck and risk. | E27: Does not qualify as AI Agent | F27: RATIONALE: TECHNOLOGY: OOB: SAP GTS Denied Party Screening AI QUALIFICATION: NO - List matching against auto-updating regulatory lists - Corporate ownership validation follows defined hierarchies - Shell company detection uses ownership rules, not learned patterns - All-party screening is systematic list checking SIEMENS CRITERIA ASSESSMENT: - Business Value: HIGH (keeps pace with 500+ weekly list changes) - Cross-business Applicability: HIGH (all international transactions) - Technical Complexity: LOW (OOB SAP GTS) - ACP Compliance: Level 1 (OOB platform) - Alignment with Initiatives: HIGH (compliance automation) - User Impact: HIGH (eliminates spreadsheet maintenance) CONCLUSION: SAP GTS provides OOB denied party screening. List matching and ownership traversal are deterministic, not AI. | G27: OOB: SAP GTS Denied Party Screening - auto-updating BIS Entity List, State Debarred lists, all-party screening | CONFIG: Define screening scope (buyer, ship-to, end-user, intermediaries) | H27: SAP GTS (OOB). Configure screening scope. | I27: All transaction parties: buyer, ship-to, end-user, intermediaries, freight forwarders; BIS Entity List; State Department debarred list; Corporate ownership data | J27: Triggered during quote validation. SAP GTS Denied Party Screening checks all parties against auto-updating denied party lists. Validates corporate ownership to detect shell companies hiding restricted entities. Screens any party in transaction chain. | K27: Party screening results per entity; Risk assessment; Beneficial owner analysis; Red flag alerts for ownership structures; Audit documentation | L27: Screening coverage (all parties checked); Hit accuracy; Entity List violation prevention; Investigation time for potential matches | N27: Low | O27: Limited direct revenue impact. Primarily operational efficiency. Consider bundling with related agents to increase value proposition. | P27: Medium | Q27: Primarily serves specific use case but adaptable. Applicable across divisions with customization. Core functionality in "Compliance Orchestration Agent" serves common business processes. | R27: Medium | S27: 1 system integration required. Systems: SAP GTS. Standard connectors and APIs available. | T27: High | U27: Standard CRM data. ACP Level 2 sufficient for implementation. | V27: Low | W27: STATUS VALIDATED - NO COMPETING INITIATIVE: Denied party screening. Checked: AF (12), DI (10), SI (9), SAP AI (16) - none address DPL screening. RECOMMENDATION: Proceed - critical compliance function. | X27: Medium | Y27: Addresses [Manual, Time-Intensive Processes] pain point. 'Denied party lists update weekly with 500+ changes...'. Moderate user impact. | Z27: Low | AA27: Limited direct revenue impact. Primarily operational efficiency. Consider bundling with related agents to increase value proposition. | AB27: Medium | AC27: Standard timeline: 3-6 months. 1 system integration. Key systems: SAP GTS.
A28: Compliance Orchestration Agent | B28: End-Use Validation Sub-Agent | C28: Validates the stated end-use of products against restricted applications (nuclear, chemical weapons, missile technology). Flags suspicious patterns: Why does a textile company need high-precision CNC machines? Requires end-use certificates for controlled items. | D28: [Missed Business Opportunities] Cannot systematically validate corporate account's stated end-use. Suspicious patterns missed: textile company ordering precision CNC machines. No red flag detection. Missed diversion risks lead to regulatory exposure and penalties. | E28: Does not qualify as AI Agent | F28: RATIONALE: TECHNOLOGY: OOB: SAP GTS End-Use Monitoring + CUSTOM: Red flag detection rules AI QUALIFICATION: NO - End-use validation against restricted categories is rule-based - "Red flag detection rules" = explicit rules, not learned anomalies - Example rule: "IF customer_industry = 'textile' AND product_category = 'CNC' THEN flag" - Rules are authored by compliance experts, not learned from data POTENTIAL AI ENHANCEMENT: Could add ML anomaly detection to identify suspicious patterns not covered by explicit rules. This would require: - Training data of past diversions/violations - ML model to score unusual product/customer combinations - Human feedback loop to improve detection SIEMENS CRITERIA ASSESSMENT: - Business Value: HIGH (detects diversion risks) - Cross-business Applicability: HIGH (all controlled products) - Technical Complexity: MEDIUM (OOB + custom rules) - ACP Compliance: Level 2 (custom rules development) - Alignment with Initiatives: MEDIUM (compliance, but custom work) - User Impact: HIGH (prevents regulatory exposure) CONCLUSION: Current design is rule-based, not AI. Could be enhanced with ML anomaly detection as future phase. | G28: OOB: SAP GTS End-Use Monitoring | CONFIG: Define restricted end-use categories | CUSTOM: Red flag detection rules for suspicious patterns (e.g., textile company + CNC machines) | H28: SAP GTS (OOB). CUSTOM rules for anomaly detection. | I28: Customer end-use declaration; Product capabilities (dual-use indicators); Corporate account industry; Order history patterns; Red flag rule definitions | J28: Triggered for controlled products. SAP GTS End-Use Monitoring validates stated end-use against product capabilities and customer industry. Custom red flag rules detect suspicious patterns (textile company ordering precision CNC). Requires end-use certificates for controlled items. | K28: End-use risk assessment (Low/Medium/High); Anomaly alerts with explanation; Required end-use certificates; Due diligence requirements; Recommended restrictions | L28: Risk detection accuracy; Diversion prevention rate; Assessment time; Dual-use misuse incidents prevented | N28: Low | O28: Limited direct revenue impact. Primarily operational efficiency. Consider bundling with related agents to increase value proposition. | P28: Medium | Q28: Primarily serves specific use case but adaptable. Applicable across divisions with customization. Core functionality in "Compliance Orchestration Agent" serves common business processes. | R28: Medium | S28: 1 system integration required. Systems: SAP GTS. Some custom development needed. Standard connectors and APIs available. | T28: High | U28: Standard CRM data. ACP Level 2 sufficient for implementation. | V28: Low | W28: STATUS VALIDATED - NO COMPETING INITIATIVE: End-use validation. Checked: AF (12), DI (10), SI (9), SAP AI (16) - none address end-use compliance. RECOMMENDATION: Proceed - unique compliance capability. | X28: Medium | Y28: Addresses [Missed Business Opportunities] pain point. 'Cannot systematically validate corporate account's stated end-use...'. Moderate user impact. | Z28: Low | AA28: Limited direct revenue impact. Primarily operational efficiency. Consider bundling with related agents to increase value proposition. | AB28: High | AC28: Extended timeline: >6 months. Complex factors: SAP integration, custom development. Plan for phased rollout.
A29: Compliance Orchestration Agent | B29: Compliance Documentation Sub-Agent | C29: Generates required export documentation: Shipper's Export Declaration (SED), Commercial Invoice with ECCN, Destination Control Statement, End-User Certificate, license applications. Maintains audit trail for customs and compliance audits. | D29: [Manual, Time-Intensive Processes] Export documentation prepared manually: Shipper's Export Declaration, Commercial Invoice with ECCN, End-User Certificates. 2-3 hours per shipment. Missing documents delay customs clearance 3-5 days. | E29: Does not qualify as AI Agent | F29: RATIONALE: TECHNOLOGY: OOB: SAP GTS Document Generation AI QUALIFICATION: NO - Document generation from templates is deterministic - Field population from transaction data is data merge - Audit trail is systematic logging - No learning, prediction, or NLP involved SIEMENS CRITERIA ASSESSMENT: - Business Value: HIGH (saves 2-3 hours per shipment) - Cross-business Applicability: HIGH (all export shipments) - Technical Complexity: LOW (OOB with template config) - ACP Compliance: Level 1 (OOB SAP GTS) - Alignment with Initiatives: HIGH (document automation) - User Impact: HIGH (prevents 3-5 day customs delays) CONCLUSION: SAP GTS OOB document generation. Template-based assembly is not AI. Rename to "Compliance Documentation Service" or similar. | G29: OOB: SAP GTS Document Generation - SED, Commercial Invoice, End-User Certificates, license applications | CONFIG: Customize document templates for Siemens branding/requirements | H29: SAP GTS (OOB). Configure document templates. | I29: All screening results from Sub-Agents 22-25; License data; Regulatory requirements by destination; Siemens document templates | J29: Triggered at quote approval for international shipments. SAP GTS Document Generation assembles required export documentation: Shipper's Export Declaration (SED), Commercial Invoice with ECCN, Destination Control Statement, End-User Certificate, license applications. Maintains audit trail. | K29: Complete export documentation package; Compliance certificate; Audit trail report; Customs filing-ready data; Document checklist status | L29: Documentation completeness (100% target); Customs clearance delay reduction; Audit readiness score; Document generation time vs. manual (2-3 hours) | N29: High | O29: Strong business impact with quantified targets: 100%, 3 hours. Addresses [Manual, Time-Intensive Processes] pain point with measurable ROI. | P29: Medium | Q29: Primarily serves specific use case but adaptable. Applicable across divisions with customization. Core functionality in "Compliance Orchestration Agent" serves common business processes. | R29: Medium | S29: 1 system integration required. Systems: SAP GTS. Standard connectors and APIs available. | T29: High | U29: Standard CRM data. ACP Level 2 sufficient for implementation. | V29: Low | W29: STATUS VALIDATED - NO COMPETING INITIATIVE: Compliance documentation. Checked: AF (12), DI (10), SI (9), SAP AI (16) - none address compliance doc generation. RECOMMENDATION: Proceed - unique capability. | X29: High | Y29: Addresses critical pain: [Manual, Time-Intensive Processes]. Specific issue: 'Export documentation prepared manually: Shipper's Export Declaration, Commercial Invoice with ECCN, End-User Certificate...'. Quantified impact in source data. | Z29: High | AA29: Strong business impact with quantified targets: 100%, 3 hours. Addresses [Manual, Time-Intensive Processes] pain point with measurable ROI. | AB29: Medium | AC29: Standard timeline: 3-6 months. 1 system integration. Key systems: SAP GTS.
A30: Compliance Orchestration Agent | B30: Regional Regulation Sub-Agent [NEW] | C30: Validates data handling compliance for B2B transactions: Are we authorized to transfer this corporate account's business contact data to Siemens entities in other countries? Do we have valid data processing agreements (DPAs) with this business customer? Ensures commercial records retention compliance. | D30: [Data Fragmentation & Siloed Information] B2B contact data handling inconsistent across Siemens regions. Cross-border transfer rules unclear. Data processing agreements scattered. No centralized view of compliance status per corporate account. | E30: Does not qualify as AI Agent | F30: RATIONALE: TECHNOLOGY: OOB: Salesforce Shield + SAP GTS + CUSTOM: Orchestration layer AI QUALIFICATION: NO - Consent validation is rule-based (Salesforce Shield) - Export compliance is rule-based (SAP GTS) - Custom orchestration coordinates both systems - Regulation applicability based on geography rules - No learning, prediction, or NLP involved SIEMENS CRITERIA ASSESSMENT: - Business Value: HIGH (centralizes compliance view) - Cross-business Applicability: HIGH (all cross-border transactions) - Technical Complexity: MEDIUM (multi-system orchestration) - ACP Compliance: Level 2 (custom orchestration) - Alignment with Initiatives: MEDIUM (compliance + integration) - User Impact: HIGH (unified compliance status) CONCLUSION: Multi-system orchestration of rule-based compliance checks. Valuable integration but not AI. Rename to "Regional Compliance Orchestration Service". | G30: OOB: Salesforce Shield (GDPR consent), SAP GTS (export compliance) | CUSTOM: Orchestration layer for B2B contact data transfers requiring both privacy AND export compliance checks | H30: Salesforce Shield + SAP GTS (OOB). CUSTOM orchestration layer. | I30: Corporate account geography and jurisdiction; Salesforce Shield consent records; Data processing purposes; GDPR/CCPA/LGPD requirements; Cross-border transfer rules | J30: Triggered during quote creation involving B2B contact data transfer. Salesforce Shield validates consent status for intended processing. SAP GTS handles export compliance. Custom orchestration layer coordinates both: determines applicable regulations, validates compliance, generates documentation. Flags non-compliant operations. | K30: Compliance status per regulation; Required consent validations; Data residency compliance; Cross-border transfer authorization; Unified compliance documentation | L30: Compliance violation prevention rate; Consent validation accuracy; Audit finding reduction; Regulatory fine avoidance | N30: Low | O30: Limited direct revenue impact. Primarily operational efficiency. Consider bundling with related agents to increase value proposition. | P30: Medium | Q30: Primarily serves specific use case but adaptable. Applicable across divisions with customization. Core functionality in "Compliance Orchestration Agent" serves common business processes. | R30: Medium | S30: 2 system integrations required. Systems: SAP GTS. Some custom development needed. Standard connectors and APIs available. | T30: High | U30: Standard CRM data. ACP Level 2 sufficient for implementation. | V30: Low | W30: STATUS VALIDATED - NO COMPETING INITIATIVE: Regional regulation handling. Checked: AF (12), DI (10), SI (9), SAP AI (16) - none address geo-specific compliance. RECOMMENDATION: Proceed - unique compliance capability. | X30: Medium | Y30: Addresses [Data Fragmentation & Siloed Information] pain point. 'B2B contact data handling inconsistent across Siemens regions...'. Moderate user impact. | Z30: Low | AA30: Limited direct revenue impact. Primarily operational efficiency. Consider bundling with related agents to increase value proposition. | AB30: High | AC30: Extended timeline: >6 months. Complex factors: SAP integration, custom development. Plan for phased rollout.
A31: Quote Routing & Approval Agent | B31: Deal Characteristic Analysis Sub-Agent | C31: Analyzes quote characteristics to determine approval requirements: deal value (>€1M requires VP approval), discount percentage (>30% requires pricing committee), non-standard terms (payment >90 days requires finance approval), strategic account status. | D31: [Inconsistent & Low-Quality Customer Interactions] Deal categorization inconsistent. Same deal type routed differently by different sales reps. Approval requirements unclear. Deals sent to wrong approvers. Inconsistent treatment creates confusion and delays. | E31: Does not qualify as AI Agent | F31: RATIONALE: TECHNOLOGY: OOB: Salesforce CPQ Deal Scoring + Flow routing AI QUALIFICATION: NO - Deal scoring uses configured rules: - Deal value >€1M = VP approval (threshold) - Discount >30% = pricing committee (threshold) - Payment >90 days = finance approval (threshold) - Strategic account = flag check - All scoring factors are deterministic comparisons - Approval requirements follow explicit policy matrix PREVIOUS OVERCLAIM CORRECTED: - "Agentforce Sales Agent explicitly mentioned for deal analysis" - but core is CPQ - "AI-assisted characteristic analysis beyond rule-based scoring" - unsupported claim - "Pattern recognition in deal characteristics" - no evidence of ML model - Own rationale admitted: "Core scoring (value, discount%, terms) is rule-based" SIEMENS CRITERIA ASSESSMENT: - Business Value: HIGH (consistent routing) - Cross-business Applicability: HIGH (all deals) - Technical Complexity: LOW (OOB CPQ) - ACP Compliance: Level 1 (OOB) - Alignment with Initiatives: HIGH - User Impact: MEDIUM CONCLUSION: Deal scoring is threshold-based business rules, not machine learning. The "AI" claim was based on adding Agentforce conversational layer, which doesn't change the deterministic core. | G31: OOB: Salesforce CPQ Deal Scoring | CONFIG: Define scoring factors (deal value, discount %, payment terms, strategic account status) | AGENTFORCE: Sales Agent analyzes deal characteristics | H31: Salesforce CPQ + Agentforce Sales Agent (OOB). Configure scoring factors. | I31: Quote details (value, products, terms); Corporate account data (segment, strategic status); Discount levels; Historical deal patterns; Approval policy thresholds | J31: Triggered after credit and compliance pass. Salesforce CPQ Deal Scoring analyzes: deal value (>€1M triggers VP), discount % (>30% triggers pricing committee), non-standard terms (>90 days payment triggers finance), strategic account status. Agentforce Sales Agent assists with deal analysis. | K31: Deal complexity score; Risk assessment; Strategic value rating; Required approval levels; Policy exceptions identified | L31: Scoring accuracy; Analysis time; Correct routing rate; Approval rejection due to wrong routing | N31: Low | O31: Limited direct revenue impact. Primarily operational efficiency. Consider bundling with related agents to increase value proposition. | P31: High | Q31: Approval workflows follow corporate governance policies applicable across all divisions. Deal thresholds and approver hierarchies are enterprise-standard. | R31: Medium | S31: 2 system integrations required. Systems: Salesforce CPQ , Agentforce Sales Agent. Standard connectors and APIs available. | T31: High | U31: Standard CRM data. ACP Level 2 sufficient for implementation. | V31: Low | W31: STATUS VALIDATED - NO COMPETING INITIATIVE: Deal characteristic analysis. Checked: AF (12), DI (10), SI (9), SAP AI (16) - none address deal analysis for routing. RECOMMENDATION: Proceed - unique workflow capability. | X31: Low | Y31: Pain point documented but limited scope: [Inconsistent & Low-Quality Customer Interactions]. May affect smaller user population. | Z31: Low | AA31: Limited direct revenue impact. Primarily operational efficiency. Consider bundling with related agents to increase value proposition. | AB31: Low | AC31: Quick win: ≤3 months. Primarily OOB configuration. Systems: Salesforce CPQ , Agentforce Sales Agent. Minimal dependencies.
A32: Quote Routing & Approval Agent | B32: Approver Selection Sub-Agent | C32: ⚠️ DUPLICATE OF Row 22 (Approval Routing) - Both use SF Flow approval routing. RECOMMEND MERGE. | Identifies the correct approvers for a quote based on: deal characteristics, organizational hierarchy, approver availability, and delegation rules. Example: Regional Sales VP is on vacation; routes to delegated authority or escalates to next level. | D32: [Manual, Time-Intensive Processes] Approver selection manual. Sales rep guesses who should approve. Vacation coverage unclear. Delegation rules undocumented. Time wasted routing to wrong people. Manual rerouting when approvers unavailable. | E32: Does not qualify as AI Agent | F32: RATIONALE: TECHNOLOGY: OOB: Salesforce Flow approval routing with org hierarchy lookup AI QUALIFICATION: NO - Approver selection follows explicit policy matrix - Org hierarchy lookup is database query - Availability checking is calendar integration - Delegation rules are configured policies - No learning, prediction, or NLP SIEMENS CRITERIA ASSESSMENT: - Business Value: HIGH (eliminates manual approver hunting) - Cross-business Applicability: HIGH (all approval workflows) - Technical Complexity: LOW (OOB Flow + integration) - ACP Compliance: Level 1 (OOB Salesforce) - Alignment with Initiatives: HIGH (process automation) - User Impact: HIGH (fastest approval path) CONCLUSION: Salesforce Flow provides matrix-based approver routing. Valuable automation but deterministic lookup, not AI. | G32: OOB: Salesforce Flow approval routing with org hierarchy lookup | CONFIG: Define approval matrix by deal type/amount/region, delegation rules, availability fallbacks | H32: Salesforce Flow (OOB). Configure approval matrix. | I32: Deal characteristics from Sub-Agent 28; Approval policy matrix; Org hierarchy (HRIS integration); Approver availability calendars; Delegation rules | J32: Triggered after deal analysis. Salesforce Flow determines required approvers based on policy matrix. Checks approver availability, current workload, vacation/delegation status. Optimizes for fastest approval path. Handles fallback routing when primary approvers unavailable. | K32: Approver list with sequence/parallel designation; Justification for each approver; Delegation assignments; Estimated approval timeline | L32: Routing accuracy; Approval cycle time; Rerouting incidents due to unavailability; Workload balance across approvers | N32: Low | O32: Limited direct revenue impact. Primarily operational efficiency. Consider bundling with related agents to increase value proposition. | P32: High | Q32: Approval workflows follow corporate governance policies applicable across all divisions. Deal thresholds and approver hierarchies are enterprise-standard. | R32: Low | S32: Straightforward implementation. Primarily OOB configuration. Systems: Salesforce native. Standard setup with minimal custom development. | T32: High | U32: Standard CRM data. ACP Level 2 sufficient for implementation. | V32: Low | W32: STATUS VALIDATED - NO COMPETING INITIATIVE: Approver selection. Checked: AF (12), DI (10), SI (9), SAP AI (16) - none address intelligent approver routing. RECOMMENDATION: Proceed - unique capability. | X32: Medium | Y32: Addresses [Manual, Time-Intensive Processes] pain point. 'Approver selection manual...'. Moderate user impact. | Z32: Low | AA32: Limited direct revenue impact. Primarily operational efficiency. Consider bundling with related agents to increase value proposition. | AB32: Low | AC32: Quick win: ≤3 months. Primarily OOB configuration. Systems: Salesforce native. Minimal dependencies.
A33: Quote Routing & Approval Agent | B33: Approval Workflow Orchestration Sub-Agent | C33: ⚠️ DUPLICATE OF Row 59 (Notifications & Approval) - Both handle approval workflows + SLA tracking. RECOMMEND MERGE. | Manages the approval workflow: sends quote packages to approvers in correct sequence (or parallel where allowed), tracks response times against SLAs (e.g., 24 hours for deals >€500K), escalates overdue approvals to management. | D33: [Manual, Time-Intensive Processes] Approvals processed sequentially: wait for VP (2 days), then Legal (2 days), then Finance (2 days). No parallel routing. No automated escalation. Manual status tracking. 5-10 days added to quote cycle. | E33: Does not qualify as AI Agent | F33: RATIONALE: TECHNOLOGY: OOB: Salesforce Flow workflow orchestration AI QUALIFICATION: NO - Workflow routing follows configured paths - SLA tracking is timer-based - Auto-escalation triggers on timeouts - Parallel/sequential logic is predefined - No learning, prediction, or NLP SIEMENS CRITERIA ASSESSMENT: - Business Value: HIGH (saves 5-10 days from cycle) - Cross-business Applicability: HIGH (all approval workflows) - Technical Complexity: LOW (OOB Flow) - ACP Compliance: Level 1 (OOB Salesforce) - Alignment with Initiatives: HIGH (process automation) - User Impact: HIGH (parallel routing, auto-escalation) CONCLUSION: Standard workflow automation. Salesforce Flow handles timer-based orchestration without AI. | G33: OOB: Salesforce Flow workflow orchestration - parallel routing, SLA tracking, auto-escalation | CONFIG: Define workflow paths, SLA thresholds (24h for >€500K deals), escalation rules | H33: Salesforce Flow (OOB). Configure SLAs and escalation. | I33: Approver selections from Sub-Agent 29; Deal justification package; SLA policies (24h for >€500K); Business calendar | J33: Triggered after approver selection. Salesforce Flow creates workflow instance. Sends notifications with deal context to approvers (parallel where allowed). Tracks responses against SLAs. Auto-escalates overdue approvals to management. Handles conditional routing based on responses. | K33: Workflow status (Pending/In Progress/Complete); Approver notifications; SLA countdown timers; Escalation triggers; Real-time tracking for sales rep | L33: On-time approval rate (target: >90%); Escalation frequency; Workflow completion time; Bottleneck identification | N33: High | O33: Strong business impact with quantified targets: >90%. Addresses [Manual, Time-Intensive Processes] pain point with measurable ROI. | P33: High | Q33: Approval workflows follow corporate governance policies applicable across all divisions. Deal thresholds and approver hierarchies are enterprise-standard. | R33: Low | S33: Straightforward implementation. Primarily OOB configuration. Systems: Salesforce native. Standard setup with minimal custom development. | T33: High | U33: Standard CRM data. ACP Level 2 sufficient for implementation. | V33: Low | W33: STATUS VALIDATED - NO COMPETING INITIATIVE: Approval workflow orchestration. Checked: AF (12), DI (10), SI (9), SAP AI (16) - none address multi-tier approval coordination. RECOMMENDATION: Proceed - unique workflow capability. | X33: High | Y33: Addresses critical pain: [Manual, Time-Intensive Processes]. Specific issue: 'Approvals processed sequentially: wait for VP (2 days), then Legal (2 days), then Finance (2 days)...'. Quantified impact in source data. | Z33: High | AA33: Strong business impact with quantified targets: >90%. Addresses [Manual, Time-Intensive Processes] pain point with measurable ROI. | AB33: Low | AC33: Quick win: ≤3 months. Primarily OOB configuration. Systems: Salesforce native. Minimal dependencies.
A34: Quote Routing & Approval Agent | B34: Approval Decision Support Sub-Agent | C34: Provides approvers with decision context: similar deals won/lost with this discount level, customer's purchase history, competitive situation, margin analysis, policy exceptions being requested. Enables faster, more informed approval decisions. | D34: [Information Overload & Decision Paralysis] Approvers receive quote with minimal context. Spend 30-60 minutes researching: customer history, similar deals, competitive situation. Information overload from 20+ pending approvals. Decision fatigue causes delays. | E34: Qualifies - Salesforce Agentforce Employee | F34: RATIONALE: TECHNOLOGY: OOB: Agentforce Employee Agent (NLG summarization) + CUSTOM: Deal benchmarking analytics AI QUALIFICATION: YES - Salesforce Agentforce Employee (with caveats) AI COMPONENTS: 1. Agentforce Employee Agent (OOB): - Natural Language Generation for context summarization - Conversational query interface for approvers - Knowledge retrieval from deal context 2. Deal Benchmarking Analytics (CUSTOM - NOT AI): - Similar deals lookup by discount/value/industry - Win rate statistics by discount tier - Margin comparison to target - This is SQL analytics, not ML HONEST ASSESSMENT: - The NLG summarization IS AI (transformer-based language model) - The conversational interface IS AI (NLP intent recognition) - The deal benchmarking is traditional analytics, not AI - Primary value is AI-assisted decision context, not autonomous decisions WHY QUALIFIES AS AI AGENT: - Agentforce Employee Agent uses LLM for summarization - NLP-based query understanding - Context-aware response generation - These are legitimate AI capabilities per Salesforce Agentforce architecture SIEMENS CRITERIA ASSESSMENT: - Business Value: HIGH (faster, informed approvals) - Cross-business Applicability: HIGH (all approvers) - Technical Complexity: MEDIUM (OOB + custom analytics) - ACP Compliance: Level 1 (Agentforce OOB) + Level 2 (custom analytics) - Alignment with Initiatives: HIGH (AI-assisted decisions) - User Impact: HIGH (approvers) CONCLUSION: Qualifies as Agentforce Employee Agent for NLG summarization and conversational interface. The AI provides decision SUPPORT (context, summaries), not decision MAKING. | G34: OOB: Salesforce Agentforce Employee Agent - NLG: Context summarization using LLM - NLP: Conversational query interface - Knowledge: Deal context retrieval | CUSTOM: Deal benchmarking analytics (SQL-based, NOT AI) - Similar deals lookup by discount/value/industry - Win rate by discount tier - Margin comparison to targets - Historical pattern analysis | CONFIG: Define deal similarity criteria, benchmark thresholds | H34: Agentforce Employee Agent (OOB). CUSTOM analytics for deal benchmarking. | I34: Deal details; Historical similar deals (won/lost); Win rate by discount level; Margin benchmarks; Policy exceptions being requested | J34: Triggered when approver opens workflow. Agentforce Employee Agent summarizes deal context. Custom analytics layer provides: similar deals at this discount level (win rate), margin analysis vs. target, customer relationship history, competitive situation. Highlights policy exceptions. | K34: Decision recommendation with confidence; Comparable deal analysis; Risk/reward summary; Suggested conditions; Policy exception justification | L34: Decision quality vs. deal outcomes; Approver satisfaction; Decision time reduction; Information completeness rating | N34: Low | O34: Limited direct revenue impact. Primarily operational efficiency. Consider bundling with related agents to increase value proposition. | P34: High | Q34: Approval workflows follow corporate governance policies applicable across all divisions. Deal thresholds and approver hierarchies are enterprise-standard. | R34: Low | S34: Straightforward implementation. Primarily OOB configuration. Systems: Agentforce Employee Agent. Standard setup with minimal custom development. | T34: Low | U34: ⚠️ POTENTIAL BLOCKER: May require ACP Level 3 due to sensitive data access. | V34: Low | W34: STATUS VALIDATED - NO COMPETING INITIATIVE: Approval decision support. Checked: AF (12), DI (10), SI (9), SAP AI (16) - none address AI-assisted approvals. RECOMMENDATION: Proceed - unique capability. | X34: High | Y34: Addresses critical pain: [Information Overload & Decision Paralysis]. Specific issue: 'Approvers receive quote with minimal context...'. Quantified impact in source data. | Z34: Low | AA34: Limited direct revenue impact. Primarily operational efficiency. Consider bundling with related agents to increase value proposition. | AB34: Medium | AC34: Standard timeline: 3-6 months. 1 system integration. Key systems: Agentforce Employee Agent. Some custom development included.
... A51: Experience Cloud Agent | B51: Partner Deal Registration Sub-Agent | C51: Automates deal registration with intelligent customer matching, conflict detection, partner eligibility validation, and deal quality scoring. Creates protected opportunities, calculates partner discounts, and manages deal protection periods with proactive engagement tracking. | D51: [Manual, Time-Intensive Processes] Deal registration approval takes 2-3 days. 30% of registrations have conflicts requiring manual resolution. No systematic deal quality assessment. Partners frustrated with slow response and unclear rejection reasons. | E51: Qualifies - Salesforce Agentforce Service | F51: RATIONALE: TECHNOLOGY: OOB: Salesforce Agentforce (Experience Cloud - Partner Community) AI QUALIFICATION: YES - But NOT from fuzzy matching - Fuzzy matching (Levenshtein, Soundex) is NOT ML - it's deterministic string algorithm - AI qualification comes from Agentforce Employee Agent NLP capabilities - NLP for natural language understanding of registration context - AI-powered conflict resolution recommendations - Intelligent priority scoring (rule-based, not ML) ⚠️ CLARIFICATION: The "customer matching using fuzzy logic" is a STRING MATCHING algorithm, not machine learning. Fuzzy matching uses edit distance calculations (O(n×m) complexity) and phonetic hashing - these are deterministic, not learned patterns. DECISION: Qualifies as AI ONLY because of Agentforce NLP capabilities, NOT fuzzy matching. | G51: OOB: Salesforce Agentforce Employee Agent + Experience Cloud (Partner) CONFIG: Customer matching automation (fuzzy string matching - NOT ML), conflict detection rules CUSTOM: Priority scoring algorithm (rule-based weighted scoring) AGENTFORCE: Employee Agent (NLP for context understanding) ⚠️ NOTE: Customer matching uses Levenshtein distance and Soundex phonetic matching - these are string algorithms, not ML. AI component is Agentforce NLP only. | H51: Salesforce Experience Cloud (Partner Community) + CRM + Territory Management | I51: Deal registration submission (partner portal); Partner account and tier information; Customer account data (SF CRM); Existing opportunity and pipeline data; Territory and partner assignment rules; Deal registration policies and approval criteria; Conflict detection rules (partner overlap, direct sales); Partner incentive and discount programs; Historical deal registration patterns; Customer relationship ownership data | J51: Triggered when partner submits deal registration through portal. Validates registration completeness, ensuring all required fields are provided (customer name, opportunity details, products, estimated value, timeline). Performs intelligent customer matching using fuzzy logic to identify existing customer accounts, preventing duplicate entries. Checks for conflicts with existing opportunities, other partner registrations, and direct sales activities. Evaluates partner eligibility based on territory rights, product authorizations, program tier, and certification status. Assesses deal registration against approval policies (minimum deal size, product mix, partner capability requirements). Scores deal quality using historical win rate data, customer profile, and competitive factors. For approved registrations, automatically creates protected opportunity in Salesforce with partner attribution. Assigns appropriate deal protection period based on opportunity stage and partner tier. Calculates partner discount and incentive eligibility, applying program rules automatically. Routes exceptional cases for manual review (conflicts, policy exceptions, strategic accounts). Sends real-time notifications to partner on approval status with clear next steps. Updates partner on opportunity progress and provides collaboration workspace with internal sales team. Tracks deal protection expiration and partner engagement to prevent shelf-ware registrations. | K51: Deal registration approval/rejection decision with rationale; Conflict detection results and resolution recommendations; Protected opportunity creation in Salesforce; Partner discount and incentive calculations; Deal protection period assignment; Collaboration workspace setup (partner + internal sales); Real-time status notifications to partner; Deal quality score and win probability; Required next actions for partner and sales team; Registration expiration tracking and alerts | L51: Deal registration processing: <4 hours (from >48 hours) Auto-approval rate: >60% of registrations Partner-sourced pipeline: >25% of total pipeline Win rate on partner deals: >30% Partner portal adoption: >80% Conflict resolution time: <24 hours Partner satisfaction with registration: >4.0/5.0 Channel revenue contribution: >20% increase | N51: High | O51: Strong business impact with quantified targets: >60%, >25%, >30%, <4 hours. Addresses [Manual, Time-Intensive Processes] pain point with measurable ROI. | P51: Medium | Q51: Primarily serves specific use case but adaptable. Partner ecosystem spans multiple divisions. Partner onboarding and deal registration processes are standardized. | R51: High | S51: Complex implementation: 3 systems (multiple platforms). Custom ML model development and training required. Estimated significant technical effort. | T51: High | U51: Standard CRM data. ACP Level 2 sufficient for implementation. | V51: Medium | W51: RELATED INITIATIVE: Partner Agent is ON HOLD (AF Tab Row 9). Function: 'Partner certification, Partner Finder Data, Hybrid Deal Reg' (SOURCE: AF Tab Row 9). Status: ON HOLD, not LIVE (SOURCE: AF Tab Row 9, Col 5). Since initiative is on hold, not direct conflict but monitor for restart. RECOMMENDATION: Proceed, but coordinate with Peter Gapp (owner) if Partner Agent restarts. | X51: High | Y51: Addresses critical pain: [Manual, Time-Intensive Processes]. Specific issue: 'Deal registration approval takes 2-3 days...'. Quantified impact in source data. | Z51: High | AA51: Strong business impact with quantified targets: >60%, >25%, >30%, <4 hours. Addresses [Manual, Time-Intensive Processes] pain point with measurable ROI. | AB51: High | AC51: Extended timeline: >6 months. Complex factors: custom development, ML model training. Plan for phased rollout.
A52: Sales Enablement Agent | B52: AI-Driven Daily Prioritization & Prospecting | C52: Leverages Generative AI to prioritize daily tasks, identify key prospects, and suggest personalized outreach strategies. The agent analyzes pipeline data, customer engagement signals, and deal velocity to recommend the highest-impact activities. Integrates with calendar and email to surface time-sensitive opportunities and automate meeting prep. Provides conversational interface for reps to ask "What should I focus on today?" and receive contextual, data-driven recommendations. | D52: [Information Overload & Decision Paralysis] Sales reps juggle 50+ accounts, 100+ leads, and multiple renewals. No systematic prioritization methodology. High-value opportunities missed. Reps spend first 1-2 hours daily deciding what to work on. | E52: Qualifies - Salesforce Agentforce Employee | F52: RATIONALE: TECHNOLOGY: OOB: Salesforce Agentforce (Employee Agent) AI QUALIFICATION: YES - Generative AI for personalized outreach suggestions - ML-based task prioritization using engagement signals - Prospect scoring and recommendation - Pattern recognition for optimal contact timing SIEMENS CRITERIA ASSESSMENT: - Business Value: HIGH (sales productivity, focus on high-value activities) - Cross-business Applicability: HIGH (all sales teams) - Technical Complexity: LOW (OOB Agentforce Employee Agent) - ACP Compliance: Level 1 (OOB Salesforce) - Alignment with Initiatives: HIGH (AI-first sales) - User Impact: HIGH (daily time savings, better prioritization) PLATFORM FIT: Salesforce Agentforce Employee Agent (OOB) CONCLUSION: Core Agentforce Employee Agent functionality. AI-driven prioritization is exactly what this agent type is designed for. | G52: OOB: Salesforce Agentforce Employee Agent CONFIG: Pipeline analysis, engagement scoring, calendar integration CUSTOM: Prioritization model tuned to Siemens sales methodology AGENTFORCE: Employee Agent with Sales Productivity actions | H52: Salesforce CRM (Sales Cloud) + Agentforce + Data Cloud + Calendar Integration | I52: Lead and contact data (SF CRM); Opportunity pipeline (SF CRM); Engagement history (emails, calls, meetings); Account health metrics; Renewal dates and signals; Historical conversion patterns; Calendar availability | J52: Triggered daily or on-demand. Agentforce Employee Agent analyzes rep's portfolio of leads, opportunities, and renewals. Applies ML scoring to prioritize by urgency, value, and win probability. Generates personalized outreach suggestions for top priorities. Identifies prospects matching ideal customer profile. Considers rep's calendar and optimal contact times. | K52: Prioritized daily task list with rationale; Personalized outreach suggestions per prospect; Prospect recommendations with fit score; Optimal contact timing; Calendar integration with suggested activities | L52: Time to first sales activity: <30 min after login High-value opportunity engagement: >80% of top deals touched daily Lead response time: <4 hours (from >24 hours) Sales rep productivity: >15% more activities/week Prioritization adoption rate: >75% of team Win rate on prioritized activities: >35% | M52: Yes | N52: High | O52: Strong business impact with quantified targets: >80%, >15%, >75%, <4 hours. Addresses [Information Overload & Decision Paralysis] pain point with measurable ROI. | P52: High | Q52: Sales productivity tools benefit all customer-facing roles. Account intelligence, deal status, and coaching apply across DI, SI, and MO. | R52: High | S52: Complex implementation: 4 systems (Salesforce CRM , Agentforce ). Estimated significant technical effort. | T52: High | U52: Standard CRM data. ACP Level 2 sufficient for implementation. | V52: High | W52: DIRECT CONFLICT: Qualification Agent is IN UAT, READY TO GO-LIVE (AF Tab Row 6). Function: 'Pick up and qualify daily SieSales Leads' (SOURCE: AF Tab Row 6). Volume: 1200 Eloqua leads/month (SOURCE: AF Tab Row 6, Col 10). Status: 'Ready to Go-Live' (SOURCE: AF Tab Row 6, Col 11). RECOMMENDATION: This is launching NOW - coordinate with Todd Jones (owner). | X52: High | Y52: Addresses critical pain: [Information Overload & Decision Paralysis]. Specific issue: 'Sales reps juggle 50+ accounts, 100+ leads, and multiple renewals...'. Quantified impact in source data. | Z52: High | AA52: Strong business impact with quantified targets: >80%, >15%, >75%, <4 hours. Addresses [Information Overload & Decision Paralysis] pain point with measurable ROI. | AB52: Medium | AC52: Standard timeline: 3-6 months. 4 system integrations. Key systems: Salesforce CRM , Agentforce . Some custom development included.
A53: Sales Enablement Agent | B53: Proactive Churn Mitigation & Action | C53: Identifies at-risk customers by analyzing product usage patterns, support ticket sentiment, billing issues, and engagement decline. Uses ML model to predict churn probability 30-90 days in advance. Suggests personalized retention actions based on customer segment, contract value, and historical success patterns. Automatically triggers retention playbooks and assigns to appropriate CSM. Provides conversational interface for reps to query "Which accounts need attention?" with AI-generated risk summaries and recommended interventions. | D53: [Missed Business Opportunities] Churn detected only after cancellation request. No proactive signals. Reactive retention offers too late. 20-30% of churned customers had visible warning signs in data. Retention actions inconsistent across team. | E53: Qualifies - Salesforce Agentforce Employee | F53: RATIONALE: TECHNOLOGY: OOB: Salesforce Agentforce (Employee Agent) AI QUALIFICATION: YES - ML-based churn prediction from usage and sentiment data - Pattern recognition for at-risk indicators - AI-generated retention recommendations ML MODEL SPECIFICATION (Churn Prediction): ├── Algorithm: LSTM (Long Short-Term Memory) neural network │ └── Handles temporal sequences in usage/engagement data ├── Training Data: 36+ months customer lifecycle data ├── Feature Engineering: │ ├── Usage sequences: Daily/weekly product usage trends │ ├── Sentiment features: NPS scores, ticket sentiment scores │ ├── Engagement decay: Login frequency decline rate │ ├── Payment signals: Days past due, payment disputes │ └── Competitive indicators: Feature request patterns ├── Target: Churn probability (0-1) at 30, 60, 90-day horizons ├── Architecture: 2-layer LSTM, 128 hidden units, dropout 0.3 ├── Validation: Time-series cross-validation, AUC-ROC > 0.80 ├── Inference: Batch scoring (nightly), triggers at threshold > 0.6 └── Retraining: Bi-weekly with recent churn outcomes TECHNOLOGY STACK: - Agentforce Employee Agent (NLP for retention playbooks) - Data Cloud (usage analytics, sentiment aggregation) - Custom LSTM model (churn prediction - CUSTOM) - CRM + Product Analytics integration | G53: OOB: Salesforce Agentforce Employee Agent + Data Cloud CONFIG: Usage analytics integration, sentiment analysis, churn scoring workflows CUSTOM: LSTM neural network churn model (2-layer, 128 units, trained on 36+ months Siemens customer data, AUC > 0.80) AGENTFORCE: Employee Agent (NLP for retention recommendations) ML MODEL: LSTM neural network processing temporal usage sequences, engagement decay rates, sentiment trends, and payment behavior. Trained on Siemens-specific customer lifecycle data. Predicts churn probability at 30/60/90-day horizons. Batch scoring nightly, bi-weekly retraining. | H53: Salesforce CRM + Agentforce + Data Cloud + Product Usage Analytics + Support System | I53: Product usage and adoption data; Customer sentiment (support tickets, NPS, surveys); Engagement decline patterns; Payment behavior trends; Contract renewal timeline; Competitive intelligence; Historical churn patterns | J53: Runs scheduled analysis of customer base. ML model scores each customer's churn risk based on usage decline, sentiment signals, payment delays, support issues, and engagement patterns. Identifies at-risk customers before explicit churn signals. Generates personalized retention actions (outreach emails, discount offers, success manager engagement). Creates tasks for follow-up calls. Tracks retention action effectiveness to improve recommendations. | K53: Churn risk scores per customer; At-risk customer alerts with contributing factors; Recommended retention actions (email, call, offer); Pre-drafted retention communications; Retention playbook per risk profile; Task queue for follow-up activities | L53: Churn rate reduction: >25% vs baseline At-risk detection lead time: >45 days before cancellation Retention action success rate: >50% Revenue saved through retention: >$1M/quarter Customer lifetime value: >10% improvement Proactive intervention rate: >70% (vs reactive) | M53: Yes | N53: High | O53: Strong business impact with quantified targets: >25%, >50%, >10%, >45 days. Addresses [Missed Business Opportunities] pain point with measurable ROI. | P53: High | Q53: Sales productivity tools benefit all customer-facing roles. Account intelligence, deal status, and coaching apply across DI, SI, and MO. | R53: High | S53: Complex implementation: 5 systems (Salesforce CRM , Agentforce ). Custom ML model development and training required. Estimated significant technical effort. | T53: Medium | U53: NEEDS REVIEW: Analyzes payment behavior TRENDS (not raw transactions). Aggregated patterns may be Level 2, but verify if individual payment data is accessed. | V53: Low | W53: STATUS VALIDATED - UNIQUE TODAY: Churn prediction. Checked: AF (12) - SieSales Employee Agent summarizes, doesn't predict churn. Checked: DI #1 (Account Planning Personal Assistant) - account summaries, not churn prediction. Checked: SI (9), SAP AI (16) - none address churn. EXPANSION RISK: Customer 360 could expand to health scores. MONITOR roadmap. RECOMMENDATION: Proceed, design to feed INTO Customer 360. | X53: High | Y53: Addresses critical pain: [Missed Business Opportunities]. Specific issue: 'Churn detected only after cancellation request...'. Quantified impact in source data. | Z53: High | AA53: Strong business impact with quantified targets: >25%, >50%, >10%, >45 days. Addresses [Missed Business Opportunities] pain point with measurable ROI. | AB53: High | AC53: Extended timeline: >6 months. Complex factors: custom development, ML model training, 5 systems. Plan for phased rollout.
A54: Sales Enablement Agent | B54: Automated Opportunity & Quote Creation | C54: ⚠️ DUPLICATE OF Row 55 (Seamless Quote Management) - Both are CPQ quote automation. RECOMMEND MERGE. | Automatically drafts opportunity records and generates quotes based on CRM data, conversation insights, and historical patterns. The agent extracts deal information from emails, calls, and meetings to pre-populate opportunity fields. Suggests optimal product configurations and pricing based on customer segment, deal size, and competitive context. Reduces data entry burden while improving CRM data quality. Provides natural language interface for reps to say "Create opportunity for conversation with [customer]" and receive complete draft records. | D54: [Manual, Time-Intensive Processes] Sales reps spend 30-45 minutes creating opportunities and drafting initial quotes. Data entry errors common. Inconsistent opportunity creation across team. Time spent on admin instead of selling. | E54: Qualifies - Salesforce Agentforce Employee | F54: RATIONALE: TECHNOLOGY: OOB: Salesforce Agentforce (Employee Agent) AI QUALIFICATION: YES - AI-assisted data extraction from conversations/emails - Intelligent field population based on context - Quote generation with AI recommendations - Learning from successful opportunity patterns SIEMENS CRITERIA ASSESSMENT: - Business Value: HIGH (admin time reduction, data quality) - Cross-business Applicability: HIGH (all sales teams) - Technical Complexity: LOW (OOB Agentforce) - ACP Compliance: Level 1 (OOB Salesforce) - Alignment with Initiatives: HIGH (sales automation, AI) - User Impact: HIGH (more selling time) PLATFORM FIT: Salesforce Agentforce Employee Agent (OOB) CONCLUSION: AI-assisted creation goes beyond simple automation. Intelligent field population and contextual recommendations qualify as AI. | G54: OOB: Salesforce Agentforce Employee Agent + CPQ CONFIG: Opportunity field mapping, quote template automation CUSTOM: Product recommendation logic, pricing optimization AGENTFORCE: Employee Agent with Opportunity Management actions | H54: Salesforce CRM (Sales Cloud) + CPQ + Agentforce + Einstein Conversation Insights | I54: Customer communication (emails, call transcripts); Account data (SF CRM); Product catalog (SF CPQ); Pricing rules and discounts; Historical similar opportunities; Rep preferences and patterns | J54: Triggered by sales rep request or email conversation detection. Agentforce Employee Agent extracts opportunity details from context (customer name, products discussed, timeline, value). Pre-populates opportunity fields using AI. Generates initial quote with recommended products based on customer profile and similar deals. Suggests pricing based on account segment and competitive context. Rep reviews and submits. | K54: Pre-populated opportunity record; Draft quote with recommended products; Pricing suggestions with rationale; Similar successful deals for reference; Required fields highlighted; One-click submission after review | L54: Opportunity creation time: <5 min (from >20 min) Quote drafting time: <10 min (from >45 min) Data entry accuracy: >95% Sales rep satisfaction: >4.0/5.0 AI opportunity adoption: >60% of new opportunities Quote-to-opportunity ratio: >1.5:1 | M54: Yes | N54: High | O54: Strong business impact with quantified targets: >95%, >60%. Addresses [Manual, Time-Intensive Processes] pain point with measurable ROI. | P54: High | Q54: Sales productivity tools benefit all customer-facing roles. Account intelligence, deal status, and coaching apply across DI, SI, and MO. | R54: High | S54: Complex implementation: 4 systems (Salesforce CRM , Agentforce ). Estimated significant technical effort. | T54: High | U54: Standard CRM data. ACP Level 2 sufficient for implementation. | V54: Low | W54: FUTURE OVERLAP ONLY: Quote creation overlaps with Quoting Agent. Checked: AF (12), DI (10), SI (9) - NO live quoting capability exists today. Quoting Agent is IN DISCUSSION (AF Tab Row 8: 'In discussion, not until May'). Status explicitly 'not until May' with 'In Year 1: 500 Users' projection. RECOMMENDATION: Proceed now - capability needed before Quoting Agent goes live. Design APIs for future Quoting Agent handoff. | X54: High | Y54: Addresses critical pain: [Manual, Time-Intensive Processes]. Specific issue: 'Sales reps spend 30-45 minutes creating opportunities and drafting initial quotes...'. Quantified impact in source data. | Z54: High | AA54: Strong business impact with quantified targets: >95%, >60%. Addresses [Manual, Time-Intensive Processes] pain point with measurable ROI. | AB54: Medium | AC54: Standard timeline: 3-6 months. 4 system integrations. Key systems: Salesforce CRM , Agentforce . Some custom development included.
